[
  {
    "stopID": "8",
    "stopQueryDate": "2019-11-10T13:51:00.825Z",
    "count": 2,
    "results": [
      {
        "Direction": "Inbound",
        "Destination": "The Point",
        "Time": "00:08:04",
        "AVLS": "00:08:44",
        "Tram": "3025",
        "Action": "a",
        "Msg Sent": "10/11/2019 13:50:58",
        "Msg Received": "10/11/2019 13:50:58",
        "Msg Processed": "10/11/2019 13:50:59",
        "XML ID": "9661",
        "Total Lag": "1.0093174",
        "Create Lag": "0.7280626",
        "Process Lag": "0.2812548"
      },
      {
        "Direction": "Outbound",
        "Destination": "Tallaght",
        "Time": "00:11:06",
        "AVLS": "00:11:46",
        "Tram": "3018",
        "Action": "a",
        "Msg Sent": "10/11/2019 13:50:58",
        "Msg Received": "10/11/2019 13:50:58",
        "Msg Processed": "10/11/2019 13:50:58",
        "XML ID": "9661",
        "Total Lag": "0.9155668",
        "Create Lag": "0.7280626",
        "Process Lag": "0.1875042"
      }
    ]
  },
  {
    "stopID": "2",
    "stopQueryDate": "2019-11-10T13:51:00.847Z",
    "count": 4,
    "results": [
      {
        "Direction": "Inbound",
        "Destination": "The Point",
        "Time": "00:03:36",
        "AVLS": "00:04:16",
        "Tram": "3016",
        "Action": "a",
        "Msg Sent": "10/11/2019 13:50:58",
        "Msg Received": "10/11/2019 13:50:58",
        "Msg Processed": "10/11/2019 13:50:58",
        "XML ID": "9661",
        "Total Lag": "0.837442",
        "Create Lag": "0.7280626",
        "Process Lag": "0.1093794"
      },
      {
        "Direction": "Inbound",
        "Destination": "The Point",
        "Time": "00:14:36",
        "AVLS": "00:15:16",
        "Tram": "3017",
        "Action": "a",
        "Msg Sent": "10/11/2019 13:50:58",
        "Msg Received": "10/11/2019 13:50:58",
        "Msg Processed": "10/11/2019 13:50:58",
        "XML ID": "9661",
        "Total Lag": "0.8843218",
        "Create Lag": "0.7280626",
        "Process Lag": "0.1562592"
      },
      {
        "Direction": "Outbound",
        "Destination": "Tallaght",
        "Time": "00:05:16",
        "AVLS": "00:05:56",
        "Tram": "3017",
        "Action": "a",
        "Msg Sent": "10/11/2019 13:50:58",
        "Msg Received": "10/11/2019 13:50:58",
        "Msg Processed": "10/11/2019 13:50:58",
        "XML ID": "9661",
        "Total Lag": "0.868697",
        "Create Lag": "0.7280626",
        "Process Lag": "0.1406344"
      },
      {
        "Direction": "Outbound",
        "Destination": "Tallaght",
        "Time": "00:13:22",
        "AVLS": "00:14:02",
        "Tram": "3021",
        "Action": "a",
        "Msg Sent": "10/11/2019 13:50:58",
        "Msg Received": "10/11/2019 13:50:58",
        "Msg Processed": "10/11/2019 13:50:58",
        "XML ID": "9661",
        "Total Lag": "0.9624435",
        "Create Lag": "0.7280626",
        "Process Lag": "0.2343809"
      }
    ]
  },
  {
    "stopID": "1",
    "stopQueryDate": "2019-11-10T13:51:00.859Z",
    "count": 4,
    "results": [
      {
        "Direction": "Inbound",
        "Destination": "The Point",
        "Time": "00:02:22",
        "AVLS": "00:03:02",
        "Tram": "3016",
        "Action": "d",
        "Msg Sent": "10/11/2019 13:50:58",
        "Msg Received": "10/11/2019 13:50:58",
        "Msg Processed": "10/11/2019 13:50:58",
        "XML ID": "9661",
        "Total Lag": "0.837442",
        "Create Lag": "0.7280626",
        "Process Lag": "0.1093794"
      },
      {
        "Direction": "Inbound",
        "Destination": "The Point",
        "Time": "00:13:22",
        "AVLS": "00:14:02",
        "Tram": "3017",
        "Action": "d",
        "Msg Sent": "10/11/2019 13:50:58",
        "Msg Received": "10/11/2019 13:50:58",
        "Msg Processed": "10/11/2019 13:50:58",
        "XML ID": "9661",
        "Total Lag": "0.8843218",
        "Create Lag": "0.7280626",
        "Process Lag": "0.1562592"
      },
      {
        "Direction": "Terminating",
        "Destination": "Tallaght",
        "Time": "00:07:22",
        "AVLS": "00:08:02",
        "Tram": "3017",
        "Action": "a",
        "Msg Sent": "10/11/2019 13:50:58",
        "Msg Received": "10/11/2019 13:50:58",
        "Msg Processed": "10/11/2019 13:50:58",
        "XML ID": "9661",
        "Total Lag": "0.8843218",
        "Create Lag": "0.7280626",
        "Process Lag": "0.1562592"
      },
      {
        "Direction": "Terminating",
        "Destination": "Tallaght",
        "Time": "00:15:28",
        "AVLS": "00:16:08",
        "Tram": "3021",
        "Action": "a",
        "Msg Sent": "10/11/2019 13:50:58",
        "Msg Received": "10/11/2019 13:50:58",
        "Msg Processed": "10/11/2019 13:50:58",
        "XML ID": "9661",
        "Total Lag": "0.9624435",
        "Create Lag": "0.7280626",
        "Process Lag": "0.2343809"
      }
    ]
  },
  {
    "stopID": "5",
    "stopQueryDate": "2019-11-10T13:51:00.884Z",
    "count": 3,
    "results": [
      {
        "Direction": "Inbound",
        "Destination": "The Point",
        "Time": "00:10:15",
        "AVLS": "00:10:55",
        "Tram": "3016",
        "Action": "a",
        "Msg Sent": "10/11/2019 13:50:58",
        "Msg Received": "10/11/2019 13:50:58",
        "Msg Processed": "10/11/2019 13:50:58",
        "XML ID": "9661",
        "Total Lag": "0.8530683",
        "Create Lag": "0.7280626",
        "Process Lag": "0.1250057"
      },
      {
        "Direction": "Outbound",
        "Destination": "Tallaght",
        "Time": "00:00:00",
        "AVLS": "00:00:17",
        "Tram": "3017",
        "Action": "a",
        "Msg Sent": "10/11/2019 13:50:58",
        "Msg Received": "10/11/2019 13:50:58",
        "Msg Processed": "10/11/2019 13:50:58",
        "XML ID": "9661",
        "Total Lag": "0.868697",
        "Create Lag": "0.7280626",
        "Process Lag": "0.1406344"
      },
      {
        "Direction": "Outbound",
        "Destination": "Tallaght",
        "Time": "00:07:43",
        "AVLS": "00:08:23",
        "Tram": "3021",
        "Action": "a",
        "Msg Sent": "10/11/2019 13:50:58",
        "Msg Received": "10/11/2019 13:50:58",
        "Msg Processed": "10/11/2019 13:50:58",
        "XML ID": "9661",
        "Total Lag": "0.9468228",
        "Create Lag": "0.7280626",
        "Process Lag": "0.2187602"
      }
    ]
  },
  {
    "stopID": "6",
    "stopQueryDate": "2019-11-10T13:51:00.905Z",
    "count": 4,
    "results": [
      {
        "Direction": "Inbound",
        "Destination": "The Point",
        "Time": "00:01:58",
        "AVLS": "00:02:38",
        "Tram": "3025",
        "Action": "a",
        "Msg Sent": "10/11/2019 13:50:58",
        "Msg Received": "10/11/2019 13:50:58",
        "Msg Processed": "10/11/2019 13:50:59",
        "XML ID": "9661",
        "Total Lag": "1.0093174",
        "Create Lag": "0.7280626",
        "Process Lag": "0.2812548"
      },
      {
        "Direction": "Inbound",
        "Destination": "The Point",
        "Time": "00:13:22",
        "AVLS": "00:14:02",
        "Tram": "3016",
        "Action": "a",
        "Msg Sent": "10/11/2019 13:50:58",
        "Msg Received": "10/11/2019 13:50:58",
        "Msg Processed": "10/11/2019 13:50:58",
        "XML ID": "9661",
        "Total Lag": "0.8530683",
        "Create Lag": "0.7280626",
        "Process Lag": "0.1250057"
      },
      {
        "Direction": "Outbound",
        "Destination": "Tallaght",
        "Time": "00:04:28",
        "AVLS": "00:05:08",
        "Tram": "3021",
        "Action": "a",
        "Msg Sent": "10/11/2019 13:50:58",
        "Msg Received": "10/11/2019 13:50:58",
        "Msg Processed": "10/11/2019 13:50:58",
        "XML ID": "9661",
        "Total Lag": "0.9468228",
        "Create Lag": "0.7280626",
        "Process Lag": "0.2187602"
      },
      {
        "Direction": "Outbound",
        "Destination": "Tallaght",
        "Time": "00:16:43",
        "AVLS": "00:17:23",
        "Tram": "3018",
        "Action": "a",
        "Msg Sent": "10/11/2019 13:50:58",
        "Msg Received": "10/11/2019 13:50:58",
        "Msg Processed": "10/11/2019 13:50:58",
        "XML ID": "9661",
        "Total Lag": "0.9155668",
        "Create Lag": "0.7280626",
        "Process Lag": "0.1875042"
      }
    ]
  },
  {
    "stopID": "7",
    "stopQueryDate": "2019-11-10T13:51:00.916Z",
    "count": 4,
    "results": [
      {
        "Direction": "Inbound",
        "Destination": "The Point",
        "Time": "00:06:28",
        "AVLS": "00:07:08",
        "Tram": "3025",
        "Action": "a",
        "Msg Sent": "10/11/2019 13:50:58",
        "Msg Received": "10/11/2019 13:50:58",
        "Msg Processed": "10/11/2019 13:50:59",
        "XML ID": "9661",
        "Total Lag": "1.0093174",
        "Create Lag": "0.7280626",
        "Process Lag": "0.2812548"
      },
      {
        "Direction": "Inbound",
        "Destination": "The Point",
        "Time": "00:17:52",
        "AVLS": "00:18:32",
        "Tram": "3016",
        "Action": "a",
        "Msg Sent": "10/11/2019 13:50:58",
        "Msg Received": "10/11/2019 13:50:58",
        "Msg Processed": "10/11/2019 13:50:58",
        "XML ID": "9661",
        "Total Lag": "0.868697",
        "Create Lag": "0.7280626",
        "Process Lag": "0.1406344"
      },
      {
        "Direction": "Outbound",
        "Destination": "Tallaght",
        "Time": "00:00:25",
        "AVLS": "00:01:05",
        "Tram": "3021",
        "Action": "a",
        "Msg Sent": "10/11/2019 13:50:58",
        "Msg Received": "10/11/2019 13:50:58",
        "Msg Processed": "10/11/2019 13:50:58",
        "XML ID": "9661",
        "Total Lag": "0.9468228",
        "Create Lag": "0.7280626",
        "Process Lag": "0.2187602"
      },
      {
        "Direction": "Outbound",
        "Destination": "Tallaght",
        "Time": "00:12:40",
        "AVLS": "00:13:20",
        "Tram": "3018",
        "Action": "a",
        "Msg Sent": "10/11/2019 13:50:58",
        "Msg Received": "10/11/2019 13:50:58",
        "Msg Processed": "10/11/2019 13:50:58",
        "XML ID": "9661",
        "Total Lag": "0.9155668",
        "Create Lag": "0.7280626",
        "Process Lag": "0.1875042"
      }
    ]
  },
  {
    "stopID": "3",
    "stopQueryDate": "2019-11-10T13:51:00.932Z",
    "count": 4,
    "results": [
      {
        "Direction": "Inbound",
        "Destination": "The Point",
        "Time": "00:05:17",
        "AVLS": "00:05:57",
        "Tram": "3016",
        "Action": "a",
        "Msg Sent": "10/11/2019 13:50:58",
        "Msg Received": "10/11/2019 13:50:58",
        "Msg Processed": "10/11/2019 13:50:58",
        "XML ID": "9661",
        "Total Lag": "0.8530683",
        "Create Lag": "0.7280626",
        "Process Lag": "0.1250057"
      },
      {
        "Direction": "Inbound",
        "Destination": "The Point",
        "Time": "00:16:17",
        "AVLS": "00:16:57",
        "Tram": "3017",
        "Action": "a",
        "Msg Sent": "10/11/2019 13:50:58",
        "Msg Received": "10/11/2019 13:50:58",
        "Msg Processed": "10/11/2019 13:50:58",
        "XML ID": "9661",
        "Total Lag": "0.8843218",
        "Create Lag": "0.7280626",
        "Process Lag": "0.1562592"
      },
      {
        "Direction": "Outbound",
        "Destination": "Tallaght",
        "Time": "00:03:41",
        "AVLS": "00:04:21",
        "Tram": "3017",
        "Action": "a",
        "Msg Sent": "10/11/2019 13:50:58",
        "Msg Received": "10/11/2019 13:50:58",
        "Msg Processed": "10/11/2019 13:50:58",
        "XML ID": "9661",
        "Total Lag": "0.868697",
        "Create Lag": "0.7280626",
        "Process Lag": "0.1406344"
      },
      {
        "Direction": "Outbound",
        "Destination": "Tallaght",
        "Time": "00:11:47",
        "AVLS": "00:12:27",
        "Tram": "3021",
        "Action": "a",
        "Msg Sent": "10/11/2019 13:50:58",
        "Msg Received": "10/11/2019 13:50:58",
        "Msg Processed": "10/11/2019 13:50:58",
        "XML ID": "9661",
        "Total Lag": "0.9624435",
        "Create Lag": "0.7280626",
        "Process Lag": "0.2343809"
      }
    ]
  },
  {
    "stopID": "10",
    "stopQueryDate": "2019-11-10T13:51:00.951Z",
    "count": 4,
    "results": [
      {
        "Direction": "Inbound",
        "Destination": "The Point",
        "Time": "00:01:36",
        "AVLS": "00:02:16",
        "Tram": "3023",
        "Action": "a",
        "Msg Sent": "10/11/2019 13:50:58",
        "Msg Received": "10/11/2019 13:50:58",
        "Msg Processed": "10/11/2019 13:50:58",
        "XML ID": "9661",
        "Total Lag": "0.9780772",
        "Create Lag": "0.7280626",
        "Process Lag": "0.2500146"
      },
      {
        "Direction": "Inbound",
        "Destination": "The Point",
        "Time": "00:11:39",
        "AVLS": "00:12:19",
        "Tram": "3025",
        "Action": "a",
        "Msg Sent": "10/11/2019 13:50:58",
        "Msg Received": "10/11/2019 13:50:58",
        "Msg Processed": "10/11/2019 13:50:59",
        "XML ID": "9661",
        "Total Lag": "1.0249461",
        "Create Lag": "0.7280626",
        "Process Lag": "0.2968835"
      },
      {
        "Direction": "Outbound",
        "Destination": "Tallaght",
        "Time": "00:07:35",
        "AVLS": "00:08:15",
        "Tram": "3018",
        "Action": "a",
        "Msg Sent": "10/11/2019 13:50:58",
        "Msg Received": "10/11/2019 13:50:58",
        "Msg Processed": "10/11/2019 13:50:58",
        "XML ID": "9661",
        "Total Lag": "0.9155668",
        "Create Lag": "0.7280626",
        "Process Lag": "0.1875042"
      },
      {
        "Direction": "Outbound",
        "Destination": "Tallaght",
        "Time": "00:17:02",
        "AVLS": "00:17:42",
        "Tram": "3005",
        "Action": "a",
        "Msg Sent": "10/11/2019 13:50:58",
        "Msg Received": "10/11/2019 13:50:58",
        "Msg Processed": "10/11/2019 13:50:58",
        "XML ID": "9661",
        "Total Lag": "0.7593222",
        "Create Lag": "0.7280626",
        "Process Lag": "0.0312596"
      }
    ]
  },
  {
    "stopID": "9",
    "stopQueryDate": "2019-11-10T13:51:00.977Z",
    "count": 4,
    "results": [
      {
        "Direction": "Inbound",
        "Destination": "The Point",
        "Time": "00:00:17",
        "AVLS": "00:00:57",
        "Tram": "3023",
        "Action": "a",
        "Msg Sent": "10/11/2019 13:50:58",
        "Msg Received": "10/11/2019 13:50:58",
        "Msg Processed": "10/11/2019 13:50:58",
        "XML ID": "9661",
        "Total Lag": "0.9624435",
        "Create Lag": "0.7280626",
        "Process Lag": "0.2343809"
      },
      {
        "Direction": "Inbound",
        "Destination": "The Point",
        "Time": "00:10:20",
        "AVLS": "00:11:00",
        "Tram": "3025",
        "Action": "a",
        "Msg Sent": "10/11/2019 13:50:58",
        "Msg Received": "10/11/2019 13:50:58",
        "Msg Processed": "10/11/2019 13:50:59",
        "XML ID": "9661",
        "Total Lag": "1.0093174",
        "Create Lag": "0.7280626",
        "Process Lag": "0.2812548"
      },
      {
        "Direction": "Outbound",
        "Destination": "Tallaght",
        "Time": "00:08:51",
        "AVLS": "00:09:31",
        "Tram": "3018",
        "Action": "a",
        "Msg Sent": "10/11/2019 13:50:58",
        "Msg Received": "10/11/2019 13:50:58",
        "Msg Processed": "10/11/2019 13:50:58",
        "XML ID": "9661",
        "Total Lag": "0.9155668",
        "Create Lag": "0.7280626",
        "Process Lag": "0.1875042"
      },
      {
        "Direction": "Outbound",
        "Destination": "Tallaght",
        "Time": "00:18:18",
        "AVLS": "00:18:58",
        "Tram": "3005",
        "Action": "a",
        "Msg Sent": "10/11/2019 13:50:58",
        "Msg Received": "10/11/2019 13:50:58",
        "Msg Processed": "10/11/2019 13:50:58",
        "XML ID": "9661",
        "Total Lag": "0.7593222",
        "Create Lag": "0.7280626",
        "Process Lag": "0.0312596"
      }
    ]
  },
  {
    "stopID": "4",
    "stopQueryDate": "2019-11-10T13:51:01.008Z",
    "count": 5,
    "results": [
      {
        "Direction": "Inbound",
        "Destination": "The Point",
        "Time": "00:08:22",
        "AVLS": "00:09:02",
        "Tram": "3016",
        "Action": "a",
        "Msg Sent": "10/11/2019 13:50:58",
        "Msg Received": "10/11/2019 13:50:58",
        "Msg Processed": "10/11/2019 13:50:58",
        "XML ID": "9661",
        "Total Lag": "0.8530683",
        "Create Lag": "0.7280626",
        "Process Lag": "0.1250057"
      },
      {
        "Direction": "Outbound",
        "Destination": "Tallaght",
        "Time": "00:01:22",
        "AVLS": "00:02:02",
        "Tram": "3017",
        "Action": "a",
        "Msg Sent": "10/11/2019 13:50:58",
        "Msg Received": "10/11/2019 13:50:58",
        "Msg Processed": "10/11/2019 13:50:58",
        "XML ID": "9661",
        "Total Lag": "0.868697",
        "Create Lag": "0.7280626",
        "Process Lag": "0.1406344"
      },
      {
        "Direction": "Outbound",
        "Destination": "Saggart",
        "Time": "00:02:52",
        "AVLS": "00:03:32",
        "Tram": "3026",
        "Action": "a",
        "Msg Sent": "10/11/2019 13:50:58",
        "Msg Received": "10/11/2019 13:50:58",
        "Msg Processed": "10/11/2019 13:50:59",
        "XML ID": "9661",
        "Total Lag": "1.0419169",
        "Create Lag": "0.7280626",
        "Process Lag": "0.3138543"
      },
      {
        "Direction": "Outbound",
        "Destination": "Tallaght",
        "Time": "00:09:28",
        "AVLS": "00:10:08",
        "Tram": "3021",
        "Action": "a",
        "Msg Sent": "10/11/2019 13:50:58",
        "Msg Received": "10/11/2019 13:50:58",
        "Msg Processed": "10/11/2019 13:50:58",
        "XML ID": "9661",
        "Total Lag": "0.9468228",
        "Create Lag": "0.7280626",
        "Process Lag": "0.2187602"
      },
      {
        "Direction": "Outbound",
        "Destination": "Saggart",
        "Time": "00:12:52",
        "AVLS": "00:13:32",
        "Tram": "3014",
        "Action": "a",
        "Msg Sent": "10/11/2019 13:50:58",
        "Msg Received": "10/11/2019 13:50:58",
        "Msg Processed": "10/11/2019 13:50:58",
        "XML ID": "9661",
        "Total Lag": "0.837442",
        "Create Lag": "0.7280626",
        "Process Lag": "0.1093794"
      }
    ]
  },
  {
    "stopID": "12",
    "stopQueryDate": "2019-11-10T13:51:01.025Z",
    "count": 4,
    "results": [
      {
        "Direction": "Inbound",
        "Destination": "The Point",
        "Time": "00:03:40",
        "AVLS": "00:04:20",
        "Tram": "3023",
        "Action": "a",
        "Msg Sent": "10/11/2019 13:50:58",
        "Msg Received": "10/11/2019 13:50:58",
        "Msg Processed": "10/11/2019 13:50:58",
        "XML ID": "9661",
        "Total Lag": "0.9780772",
        "Create Lag": "0.7280626",
        "Process Lag": "0.2500146"
      },
      {
        "Direction": "Inbound",
        "Destination": "The Point",
        "Time": "00:13:43",
        "AVLS": "00:14:23",
        "Tram": "3025",
        "Action": "a",
        "Msg Sent": "10/11/2019 13:50:58",
        "Msg Received": "10/11/2019 13:50:58",
        "Msg Processed": "10/11/2019 13:50:59",
        "XML ID": "9661",
        "Total Lag": "1.0249461",
        "Create Lag": "0.7280626",
        "Process Lag": "0.2968835"
      },
      {
        "Direction": "Outbound",
        "Destination": "Tallaght",
        "Time": "00:05:34",
        "AVLS": "00:06:14",
        "Tram": "3018",
        "Action": "a",
        "Msg Sent": "10/11/2019 13:50:58",
        "Msg Received": "10/11/2019 13:50:58",
        "Msg Processed": "10/11/2019 13:50:58",
        "XML ID": "9661",
        "Total Lag": "0.8999384",
        "Create Lag": "0.7280626",
        "Process Lag": "0.1718758"
      },
      {
        "Direction": "Outbound",
        "Destination": "Tallaght",
        "Time": "00:15:01",
        "AVLS": "00:15:41",
        "Tram": "3005",
        "Action": "a",
        "Msg Sent": "10/11/2019 13:50:58",
        "Msg Received": "10/11/2019 13:50:58",
        "Msg Processed": "10/11/2019 13:50:58",
        "XML ID": "9661",
        "Total Lag": "0.7593222",
        "Create Lag": "0.7280626",
        "Process Lag": "0.0312596"
      }
    ]
  },
  {
    "stopID": "11",
    "stopQueryDate": "2019-11-10T13:51:01.042Z",
    "count": 4,
    "results": [
      {
        "Direction": "Inbound",
        "Destination": "The Point",
        "Time": "00:02:34",
        "AVLS": "00:03:14",
        "Tram": "3023",
        "Action": "a",
        "Msg Sent": "10/11/2019 13:50:58",
        "Msg Received": "10/11/2019 13:50:58",
        "Msg Processed": "10/11/2019 13:50:58",
        "XML ID": "9661",
        "Total Lag": "0.9780772",
        "Create Lag": "0.7280626",
        "Process Lag": "0.2500146"
      },
      {
        "Direction": "Inbound",
        "Destination": "The Point",
        "Time": "00:12:37",
        "AVLS": "00:13:17",
        "Tram": "3025",
        "Action": "a",
        "Msg Sent": "10/11/2019 13:50:58",
        "Msg Received": "10/11/2019 13:50:58",
        "Msg Processed": "10/11/2019 13:50:59",
        "XML ID": "9661",
        "Total Lag": "1.0249461",
        "Create Lag": "0.7280626",
        "Process Lag": "0.2968835"
      },
      {
        "Direction": "Outbound",
        "Destination": "Tallaght",
        "Time": "00:06:39",
        "AVLS": "00:07:19",
        "Tram": "3018",
        "Action": "a",
        "Msg Sent": "10/11/2019 13:50:58",
        "Msg Received": "10/11/2019 13:50:58",
        "Msg Processed": "10/11/2019 13:50:58",
        "XML ID": "9661",
        "Total Lag": "0.8999384",
        "Create Lag": "0.7280626",
        "Process Lag": "0.1718758"
      },
      {
        "Direction": "Outbound",
        "Destination": "Tallaght",
        "Time": "00:16:06",
        "AVLS": "00:16:46",
        "Tram": "3005",
        "Action": "a",
        "Msg Sent": "10/11/2019 13:50:58",
        "Msg Received": "10/11/2019 13:50:58",
        "Msg Processed": "10/11/2019 13:50:58",
        "XML ID": "9661",
        "Total Lag": "0.7593222",
        "Create Lag": "0.7280626",
        "Process Lag": "0.0312596"
      }
    ]
  },
  {
    "stopID": "23",
    "stopQueryDate": "2019-11-10T13:51:01.050Z",
    "count": 0,
    "results": []
  },
  {
    "stopID": "18",
    "stopQueryDate": "2019-11-10T13:51:01.061Z",
    "count": 4,
    "results": [
      {
        "Direction": "Inbound",
        "Destination": "The Point",
        "Time": "00:06:39",
        "AVLS": "00:07:19",
        "Tram": "4005",
        "Action": "a",
        "Msg Sent": "10/11/2019 13:50:58",
        "Msg Received": "10/11/2019 13:50:59",
        "Msg Processed": "10/11/2019 13:50:59",
        "XML ID": "9662",
        "Total Lag": "1.2137973",
        "Create Lag": "1.1981717",
        "Process Lag": "0.0156256"
      },
      {
        "Direction": "Inbound",
        "Destination": "The Point",
        "Time": "00:16:01",
        "AVLS": "00:16:41",
        "Tram": "3023",
        "Action": "a",
        "Msg Sent": "10/11/2019 13:50:58",
        "Msg Received": "10/11/2019 13:50:58",
        "Msg Processed": "10/11/2019 13:50:59",
        "XML ID": "9661",
        "Total Lag": "1.0093174",
        "Create Lag": "0.7280626",
        "Process Lag": "0.2812548"
      },
      {
        "Direction": "Outbound",
        "Destination": "Tallaght",
        "Time": "00:02:31",
        "AVLS": "00:03:11",
        "Tram": "3005",
        "Action": "a",
        "Msg Sent": "10/11/2019 13:50:58",
        "Msg Received": "10/11/2019 13:50:58",
        "Msg Processed": "10/11/2019 13:50:58",
        "XML ID": "9661",
        "Total Lag": "0.7280626",
        "Create Lag": "0.7280626",
        "Process Lag": "0"
      },
      {
        "Direction": "Outbound",
        "Destination": "Tallaght",
        "Time": "00:12:00",
        "AVLS": "00:12:40",
        "Tram": "4002",
        "Action": "a",
        "Msg Sent": "10/11/2019 13:50:58",
        "Msg Received": "10/11/2019 13:50:58",
        "Msg Processed": "10/11/2019 13:50:59",
        "XML ID": "9661",
        "Total Lag": "1.0731743",
        "Create Lag": "0.7280626",
        "Process Lag": "0.3451117"
      }
    ]
  },
  {
    "stopID": "14",
    "stopQueryDate": "2019-11-10T13:51:01.081Z",
    "count": 4,
    "results": [
      {
        "Direction": "Inbound",
        "Destination": "The Point",
        "Time": "00:06:23",
        "AVLS": "00:07:03",
        "Tram": "3023",
        "Action": "a",
        "Msg Sent": "10/11/2019 13:50:58",
        "Msg Received": "10/11/2019 13:50:58",
        "Msg Processed": "10/11/2019 13:50:58",
        "XML ID": "9661",
        "Total Lag": "0.9936926",
        "Create Lag": "0.7280626",
        "Process Lag": "0.26563"
      },
      {
        "Direction": "Inbound",
        "Destination": "The Point",
        "Time": "00:16:26",
        "AVLS": "00:17:06",
        "Tram": "3025",
        "Action": "a",
        "Msg Sent": "10/11/2019 13:50:58",
        "Msg Received": "10/11/2019 13:50:58",
        "Msg Processed": "10/11/2019 13:50:59",
        "XML ID": "9661",
        "Total Lag": "1.0409487",
        "Create Lag": "0.7280626",
        "Process Lag": "0.3128861"
      },
      {
        "Direction": "Outbound",
        "Destination": "Tallaght",
        "Time": "00:02:53",
        "AVLS": "00:03:33",
        "Tram": "3018",
        "Action": "a",
        "Msg Sent": "10/11/2019 13:50:58",
        "Msg Received": "10/11/2019 13:50:58",
        "Msg Processed": "10/11/2019 13:50:58",
        "XML ID": "9661",
        "Total Lag": "0.8999384",
        "Create Lag": "0.7280626",
        "Process Lag": "0.1718758"
      },
      {
        "Direction": "Outbound",
        "Destination": "Tallaght",
        "Time": "00:12:20",
        "AVLS": "00:13:00",
        "Tram": "3005",
        "Action": "a",
        "Msg Sent": "10/11/2019 13:50:58",
        "Msg Received": "10/11/2019 13:50:58",
        "Msg Processed": "10/11/2019 13:50:58",
        "XML ID": "9661",
        "Total Lag": "0.7437405",
        "Create Lag": "0.7280626",
        "Process Lag": "0.0156779"
      }
    ]
  },
  {
    "stopID": "13",
    "stopQueryDate": "2019-11-10T13:51:01.108Z",
    "count": 4,
    "results": [
      {
        "Direction": "Inbound",
        "Destination": "The Point",
        "Time": "00:05:24",
        "AVLS": "00:06:04",
        "Tram": "3023",
        "Action": "a",
        "Msg Sent": "10/11/2019 13:50:58",
        "Msg Received": "10/11/2019 13:50:58",
        "Msg Processed": "10/11/2019 13:50:58",
        "XML ID": "9661",
        "Total Lag": "0.9780772",
        "Create Lag": "0.7280626",
        "Process Lag": "0.2500146"
      },
      {
        "Direction": "Inbound",
        "Destination": "The Point",
        "Time": "00:15:27",
        "AVLS": "00:16:07",
        "Tram": "3025",
        "Action": "a",
        "Msg Sent": "10/11/2019 13:50:58",
        "Msg Received": "10/11/2019 13:50:58",
        "Msg Processed": "10/11/2019 13:50:59",
        "XML ID": "9661",
        "Total Lag": "1.0249461",
        "Create Lag": "0.7280626",
        "Process Lag": "0.2968835"
      },
      {
        "Direction": "Outbound",
        "Destination": "Tallaght",
        "Time": "00:03:53",
        "AVLS": "00:04:33",
        "Tram": "3018",
        "Action": "a",
        "Msg Sent": "10/11/2019 13:50:58",
        "Msg Received": "10/11/2019 13:50:58",
        "Msg Processed": "10/11/2019 13:50:58",
        "XML ID": "9661",
        "Total Lag": "0.8999384",
        "Create Lag": "0.7280626",
        "Process Lag": "0.1718758"
      },
      {
        "Direction": "Outbound",
        "Destination": "Tallaght",
        "Time": "00:13:20",
        "AVLS": "00:14:00",
        "Tram": "3005",
        "Action": "a",
        "Msg Sent": "10/11/2019 13:50:58",
        "Msg Received": "10/11/2019 13:50:58",
        "Msg Processed": "10/11/2019 13:50:58",
        "XML ID": "9661",
        "Total Lag": "0.7437405",
        "Create Lag": "0.7280626",
        "Process Lag": "0.0156779"
      }
    ]
  },
  {
    "stopID": "16",
    "stopQueryDate": "2019-11-10T13:51:01.126Z",
    "count": 4,
    "results": [
      {
        "Direction": "Inbound",
        "Destination": "The Point",
        "Time": "00:01:33",
        "AVLS": "00:02:13",
        "Tram": "4005",
        "Action": "a",
        "Msg Sent": "10/11/2019 13:50:58",
        "Msg Received": "10/11/2019 13:50:59",
        "Msg Processed": "10/11/2019 13:50:59",
        "XML ID": "9662",
        "Total Lag": "1.1981717",
        "Create Lag": "1.1981717",
        "Process Lag": "0"
      },
      {
        "Direction": "Inbound",
        "Destination": "The Point",
        "Time": "00:10:55",
        "AVLS": "00:11:35",
        "Tram": "3023",
        "Action": "a",
        "Msg Sent": "10/11/2019 13:50:58",
        "Msg Received": "10/11/2019 13:50:58",
        "Msg Processed": "10/11/2019 13:50:58",
        "XML ID": "9661",
        "Total Lag": "0.9936926",
        "Create Lag": "0.7280626",
        "Process Lag": "0.26563"
      },
      {
        "Direction": "Outbound",
        "Destination": "Tallaght",
        "Time": "00:07:10",
        "AVLS": "00:07:50",
        "Tram": "3005",
        "Action": "a",
        "Msg Sent": "10/11/2019 13:50:58",
        "Msg Received": "10/11/2019 13:50:58",
        "Msg Processed": "10/11/2019 13:50:58",
        "XML ID": "9661",
        "Total Lag": "0.7437405",
        "Create Lag": "0.7280626",
        "Process Lag": "0.0156779"
      },
      {
        "Direction": "Outbound",
        "Destination": "Tallaght",
        "Time": "00:16:39",
        "AVLS": "00:17:19",
        "Tram": "4002",
        "Action": "a",
        "Msg Sent": "10/11/2019 13:50:58",
        "Msg Received": "10/11/2019 13:50:59",
        "Msg Processed": "10/11/2019 13:50:59",
        "XML ID": "9662",
        "Total Lag": "1.1981717",
        "Create Lag": "1.1981717",
        "Process Lag": "0"
      }
    ]
  },
  {
    "stopID": "36",
    "stopQueryDate": "2019-11-10T13:51:01.137Z",
    "count": 2,
    "results": [
      {
        "Direction": "Inbound",
        "Destination": "Broombridge",
        "Time": "00:07:41",
        "AVLS": "00:08:21",
        "Tram": "5031",
        "Action": "a",
        "Msg Sent": "10/11/2019 13:50:51",
        "Msg Received": "10/11/2019 13:50:51",
        "Msg Processed": "10/11/2019 13:50:51",
        "XML ID": "9658",
        "Total Lag": "0.7280596",
        "Create Lag": "0.6499364",
        "Process Lag": "0.0781232"
      },
      {
        "Direction": "Outbound",
        "Destination": "Bride's Glen",
        "Time": "00:08:37",
        "AVLS": "00:09:17",
        "Tram": "5004",
        "Action": "a",
        "Msg Sent": "10/11/2019 13:50:58",
        "Msg Received": "10/11/2019 13:50:59",
        "Msg Processed": "10/11/2019 13:50:59",
        "XML ID": "9662",
        "Total Lag": "1.3231783",
        "Create Lag": "1.1981717",
        "Process Lag": "0.1250066"
      }
    ]
  },
  {
    "stopID": "43",
    "stopQueryDate": "2019-11-10T13:51:01.146Z",
    "count": 2,
    "results": [
      {
        "Direction": "Inbound",
        "Destination": "Broombridge",
        "Time": "00:09:26",
        "AVLS": "00:10:06",
        "Tram": "5021",
        "Action": "a",
        "Msg Sent": "10/11/2019 13:50:58",
        "Msg Received": "10/11/2019 13:50:59",
        "Msg Processed": "10/11/2019 13:50:59",
        "XML ID": "9662",
        "Total Lag": "1.511649",
        "Create Lag": "1.1981717",
        "Process Lag": "0.3134773"
      },
      {
        "Direction": "Outbound",
        "Destination": "Bride's Glen",
        "Time": "00:09:46",
        "AVLS": "00:10:26",
        "Tram": "5017",
        "Action": "a",
        "Msg Sent": "10/11/2019 13:50:58",
        "Msg Received": "10/11/2019 13:50:59",
        "Msg Processed": "10/11/2019 13:50:59",
        "XML ID": "9662",
        "Total Lag": "1.4794257",
        "Create Lag": "1.1981717",
        "Process Lag": "0.281254"
      }
    ]
  },
  {
    "stopID": "58",
    "stopQueryDate": "2019-11-10T13:51:01.149Z",
    "count": 0,
    "results": []
  },
  {
    "stopID": "42",
    "stopQueryDate": "2019-11-10T13:51:01.229Z",
    "count": 3,
    "results": [
      {
        "Direction": "Inbound",
        "Destination": "Broombridge",
        "Time": "00:11:02",
        "AVLS": "00:11:42",
        "Tram": "5021",
        "Action": "a",
        "Msg Sent": "10/11/2019 13:50:58",
        "Msg Received": "10/11/2019 13:50:59",
        "Msg Processed": "10/11/2019 13:50:59",
        "XML ID": "9662",
        "Total Lag": "1.511649",
        "Create Lag": "1.1981717",
        "Process Lag": "0.3134773"
      },
      {
        "Direction": "Outbound",
        "Destination": "Bride's Glen",
        "Time": "00:08:13",
        "AVLS": "00:08:53",
        "Tram": "5017",
        "Action": "a",
        "Msg Sent": "10/11/2019 13:50:58",
        "Msg Received": "10/11/2019 13:50:59",
        "Msg Processed": "10/11/2019 13:50:59",
        "XML ID": "9662",
        "Total Lag": "1.4637973",
        "Create Lag": "1.1981717",
        "Process Lag": "0.2656256"
      },
      {
        "Direction": "Outbound",
        "Destination": "Bride's Glen",
        "Time": "00:17:59",
        "AVLS": "00:18:39",
        "Tram": "5004",
        "Action": "a",
        "Msg Sent": "10/11/2019 13:50:58",
        "Msg Received": "10/11/2019 13:50:59",
        "Msg Processed": "10/11/2019 13:50:59",
        "XML ID": "9662",
        "Total Lag": "1.3231783",
        "Create Lag": "1.1981717",
        "Process Lag": "0.1250066"
      }
    ]
  },
  {
    "stopID": "39",
    "stopQueryDate": "2019-11-10T13:51:01.240Z",
    "count": 4,
    "results": [
      {
        "Direction": "Inbound",
        "Destination": "Broombridge",
        "Time": "00:02:02",
        "AVLS": "00:02:42",
        "Tram": "5031",
        "Action": "a",
        "Msg Sent": "10/11/2019 13:50:51",
        "Msg Received": "10/11/2019 13:50:51",
        "Msg Processed": "10/11/2019 13:50:51",
        "XML ID": "9658",
        "Total Lag": "0.7124416",
        "Create Lag": "0.6499364",
        "Process Lag": "0.0625052"
      },
      {
        "Direction": "Inbound",
        "Destination": "Broombridge",
        "Time": "00:14:43",
        "AVLS": "00:15:23",
        "Tram": "5021",
        "Action": "a",
        "Msg Sent": "10/11/2019 13:50:58",
        "Msg Received": "10/11/2019 13:50:59",
        "Msg Processed": "10/11/2019 13:50:59",
        "XML ID": "9662",
        "Total Lag": "1.5272901",
        "Create Lag": "1.1981717",
        "Process Lag": "0.3291184"
      },
      {
        "Direction": "Outbound",
        "Destination": "Bride's Glen",
        "Time": "00:04:37",
        "AVLS": "00:05:17",
        "Tram": "5017",
        "Action": "a",
        "Msg Sent": "10/11/2019 13:50:58",
        "Msg Received": "10/11/2019 13:50:59",
        "Msg Processed": "10/11/2019 13:50:59",
        "XML ID": "9662",
        "Total Lag": "1.4637973",
        "Create Lag": "1.1981717",
        "Process Lag": "0.2656256"
      },
      {
        "Direction": "Outbound",
        "Destination": "Bride's Glen",
        "Time": "00:14:23",
        "AVLS": "00:15:03",
        "Tram": "5004",
        "Action": "a",
        "Msg Sent": "10/11/2019 13:50:58",
        "Msg Received": "10/11/2019 13:50:59",
        "Msg Processed": "10/11/2019 13:50:59",
        "XML ID": "9662",
        "Total Lag": "1.3231783",
        "Create Lag": "1.1981717",
        "Process Lag": "0.1250066"
      }
    ]
  },
  {
    "stopID": "35",
    "stopQueryDate": "2019-11-10T13:51:01.257Z",
    "count": 3,
    "results": [
      {
        "Direction": "Inbound",
        "Destination": "Broombridge",
        "Time": "00:00:00",
        "AVLS": "00:00:00",
        "Tram": "5011",
        "Action": "a",
        "Msg Sent": "10/11/2019 13:50:31",
        "Msg Received": "10/11/2019 13:50:31",
        "Msg Processed": "10/11/2019 13:50:31",
        "XML ID": "9649",
        "Total Lag": "0.6095455",
        "Create Lag": "0.5001695",
        "Process Lag": "0.109376"
      },
      {
        "Direction": "Inbound",
        "Destination": "Broombridge",
        "Time": "00:09:16",
        "AVLS": "00:09:56",
        "Tram": "5031",
        "Action": "a",
        "Msg Sent": "10/11/2019 13:50:51",
        "Msg Received": "10/11/2019 13:50:51",
        "Msg Processed": "10/11/2019 13:50:51",
        "XML ID": "9658",
        "Total Lag": "0.7280596",
        "Create Lag": "0.6499364",
        "Process Lag": "0.0781232"
      },
      {
        "Direction": "Outbound",
        "Destination": "Bride's Glen",
        "Time": "00:07:16",
        "AVLS": "00:07:56",
        "Tram": "5004",
        "Action": "a",
        "Msg Sent": "10/11/2019 13:50:58",
        "Msg Received": "10/11/2019 13:50:59",
        "Msg Processed": "10/11/2019 13:50:59",
        "XML ID": "9662",
        "Total Lag": "1.3075584",
        "Create Lag": "1.1981717",
        "Process Lag": "0.1093867"
      }
    ]
  },
  {
    "stopID": "28",
    "stopQueryDate": "2019-11-10T13:51:01.289Z",
    "count": 3,
    "results": [
      {
        "Direction": "Inbound",
        "Destination": "Broombridge",
        "Time": "00:00:30",
        "AVLS": "00:01:10",
        "Tram": "5003",
        "Action": "a",
        "Msg Sent": "10/11/2019 13:50:58",
        "Msg Received": "10/11/2019 13:50:59",
        "Msg Processed": "10/11/2019 13:50:59",
        "XML ID": "9662",
        "Total Lag": "1.2450509",
        "Create Lag": "1.1981717",
        "Process Lag": "0.0468792"
      },
      {
        "Direction": "Inbound",
        "Destination": "Broombridge",
        "Time": "00:11:16",
        "AVLS": "00:11:56",
        "Tram": "5011",
        "Action": "a",
        "Msg Sent": "10/11/2019 13:50:58",
        "Msg Received": "10/11/2019 13:50:59",
        "Msg Processed": "10/11/2019 13:50:59",
        "XML ID": "9662",
        "Total Lag": "1.4169378",
        "Create Lag": "1.1981717",
        "Process Lag": "0.2187661"
      },
      {
        "Direction": "Outbound",
        "Destination": "Bride's Glen",
        "Time": "00:08:49",
        "AVLS": "00:09:29",
        "Tram": "5007",
        "Action": "a",
        "Msg Sent": "10/11/2019 13:50:58",
        "Msg Received": "10/11/2019 13:50:59",
        "Msg Processed": "10/11/2019 13:50:59",
        "XML ID": "9662",
        "Total Lag": "1.3544312",
        "Create Lag": "1.1981717",
        "Process Lag": "0.1562595"
      }
    ]
  },
  {
    "stopID": "20",
    "stopQueryDate": "2019-11-10T13:51:01.298Z",
    "count": 3,
    "results": [
      {
        "Direction": "Inbound",
        "Destination": "The Point",
        "Time": "00:10:32",
        "AVLS": "00:11:12",
        "Tram": "4005",
        "Action": "a",
        "Msg Sent": "10/11/2019 13:50:58",
        "Msg Received": "10/11/2019 13:50:59",
        "Msg Processed": "10/11/2019 13:50:59",
        "XML ID": "9662",
        "Total Lag": "1.2137973",
        "Create Lag": "1.1981717",
        "Process Lag": "0.0156256"
      },
      {
        "Direction": "Outbound",
        "Destination": "Tallaght",
        "Time": "00:08:20",
        "AVLS": "00:09:00",
        "Tram": "4002",
        "Action": "a",
        "Msg Sent": "10/11/2019 13:50:58",
        "Msg Received": "10/11/2019 13:50:58",
        "Msg Processed": "10/11/2019 13:50:59",
        "XML ID": "9661",
        "Total Lag": "1.0731743",
        "Create Lag": "0.7280626",
        "Process Lag": "0.3451117"
      },
      {
        "Direction": "Outbound",
        "Destination": "Tallaght",
        "Time": "00:19:03",
        "AVLS": "00:19:43",
        "Tram": "3011",
        "Action": "a",
        "Msg Sent": "10/11/2019 13:50:58",
        "Msg Received": "10/11/2019 13:50:58",
        "Msg Processed": "10/11/2019 13:50:58",
        "XML ID": "9661",
        "Total Lag": "0.8218179",
        "Create Lag": "0.7280626",
        "Process Lag": "0.0937553"
      }
    ]
  },
  {
    "stopID": "45",
    "stopQueryDate": "2019-11-10T13:51:01.318Z",
    "count": 4,
    "results": [
      {
        "Direction": "Inbound",
        "Destination": "Broombridge",
        "Time": "00:06:53",
        "AVLS": "00:07:33",
        "Tram": "5021",
        "Action": "a",
        "Msg Sent": "10/11/2019 13:50:58",
        "Msg Received": "10/11/2019 13:50:59",
        "Msg Processed": "10/11/2019 13:50:59",
        "XML ID": "9662",
        "Total Lag": "1.511649",
        "Create Lag": "1.1981717",
        "Process Lag": "0.3134773"
      },
      {
        "Direction": "Inbound",
        "Destination": "Broombridge",
        "Time": "00:18:53",
        "AVLS": "00:19:33",
        "Tram": "5015",
        "Action": "a",
        "Msg Sent": "10/11/2019 13:50:58",
        "Msg Received": "10/11/2019 13:50:59",
        "Msg Processed": "10/11/2019 13:50:59",
        "XML ID": "9662",
        "Total Lag": "1.4481832",
        "Create Lag": "1.1981717",
        "Process Lag": "0.2500115"
      },
      {
        "Direction": "Outbound",
        "Destination": "Bride's Glen",
        "Time": "00:00:00",
        "AVLS": "00:00:00",
        "Tram": "5015",
        "Action": "a",
        "Msg Sent": "10/11/2019 13:50:51",
        "Msg Received": "10/11/2019 13:50:51",
        "Msg Processed": "10/11/2019 13:50:51",
        "XML ID": "9658",
        "Total Lag": "0.7436861",
        "Create Lag": "0.6499364",
        "Process Lag": "0.0937497"
      },
      {
        "Direction": "Outbound",
        "Destination": "Bride's Glen",
        "Time": "00:12:19",
        "AVLS": "00:12:59",
        "Tram": "5017",
        "Action": "a",
        "Msg Sent": "10/11/2019 13:50:58",
        "Msg Received": "10/11/2019 13:50:59",
        "Msg Processed": "10/11/2019 13:50:59",
        "XML ID": "9662",
        "Total Lag": "1.4794257",
        "Create Lag": "1.1981717",
        "Process Lag": "0.281254"
      }
    ]
  },
  {
    "stopID": "25",
    "stopQueryDate": "2019-11-10T13:51:01.339Z",
    "count": 4,
    "results": [
      {
        "Direction": "Inbound",
        "Destination": "Broombridge",
        "Time": "00:05:32",
        "AVLS": "00:06:12",
        "Tram": "5003",
        "Action": "a",
        "Msg Sent": "10/11/2019 13:50:58",
        "Msg Received": "10/11/2019 13:50:59",
        "Msg Processed": "10/11/2019 13:50:59",
        "XML ID": "9662",
        "Total Lag": "1.2607258",
        "Create Lag": "1.1981717",
        "Process Lag": "0.0625541"
      },
      {
        "Direction": "Inbound",
        "Destination": "Broombridge",
        "Time": "00:16:18",
        "AVLS": "00:16:58",
        "Tram": "5011",
        "Action": "a",
        "Msg Sent": "10/11/2019 13:50:58",
        "Msg Received": "10/11/2019 13:50:59",
        "Msg Processed": "10/11/2019 13:50:59",
        "XML ID": "9662",
        "Total Lag": "1.4169378",
        "Create Lag": "1.1981717",
        "Process Lag": "0.2187661"
      },
      {
        "Direction": "Outbound",
        "Destination": "Bride's Glen",
        "Time": "00:02:47",
        "AVLS": "00:03:27",
        "Tram": "5007",
        "Action": "a",
        "Msg Sent": "10/11/2019 13:50:58",
        "Msg Received": "10/11/2019 13:50:59",
        "Msg Processed": "10/11/2019 13:50:59",
        "XML ID": "9662",
        "Total Lag": "1.3387994",
        "Create Lag": "1.1981717",
        "Process Lag": "0.1406277"
      },
      {
        "Direction": "Outbound",
        "Destination": "Bride's Glen",
        "Time": "00:13:38",
        "AVLS": "00:14:18",
        "Tram": "5008",
        "Action": "a",
        "Msg Sent": "10/11/2019 13:50:58",
        "Msg Received": "10/11/2019 13:50:59",
        "Msg Processed": "10/11/2019 13:50:59",
        "XML ID": "9662",
        "Total Lag": "1.3856764",
        "Create Lag": "1.1981717",
        "Process Lag": "0.1875047"
      }
    ]
  },
  {
    "stopID": "46",
    "stopQueryDate": "2019-11-10T13:51:01.349Z",
    "count": 4,
    "results": [
      {
        "Direction": "Inbound",
        "Destination": "Broombridge",
        "Time": "00:05:31",
        "AVLS": "00:06:11",
        "Tram": "5021",
        "Action": "a",
        "Msg Sent": "10/11/2019 13:50:58",
        "Msg Received": "10/11/2019 13:50:59",
        "Msg Processed": "10/11/2019 13:50:59",
        "XML ID": "9662",
        "Total Lag": "1.511649",
        "Create Lag": "1.1981717",
        "Process Lag": "0.3134773"
      },
      {
        "Direction": "Inbound",
        "Destination": "Broombridge",
        "Time": "00:17:31",
        "AVLS": "00:18:11",
        "Tram": "5015",
        "Action": "a",
        "Msg Sent": "10/11/2019 13:50:58",
        "Msg Received": "10/11/2019 13:50:59",
        "Msg Processed": "10/11/2019 13:50:59",
        "XML ID": "9662",
        "Total Lag": "1.4481832",
        "Create Lag": "1.1981717",
        "Process Lag": "0.2500115"
      },
      {
        "Direction": "Outbound",
        "Destination": "Bride's Glen",
        "Time": "00:00:35",
        "AVLS": "00:01:15",
        "Tram": "5015",
        "Action": "a",
        "Msg Sent": "10/11/2019 13:50:58",
        "Msg Received": "10/11/2019 13:50:59",
        "Msg Processed": "10/11/2019 13:50:59",
        "XML ID": "9662",
        "Total Lag": "1.4325589",
        "Create Lag": "1.1981717",
        "Process Lag": "0.2343872"
      },
      {
        "Direction": "Outbound",
        "Destination": "Bride's Glen",
        "Time": "00:13:42",
        "AVLS": "00:14:22",
        "Tram": "5017",
        "Action": "a",
        "Msg Sent": "10/11/2019 13:50:58",
        "Msg Received": "10/11/2019 13:50:59",
        "Msg Processed": "10/11/2019 13:50:59",
        "XML ID": "9662",
        "Total Lag": "1.4973701",
        "Create Lag": "1.1981717",
        "Process Lag": "0.2991984"
      }
    ]
  },
  {
    "stopID": "44",
    "stopQueryDate": "2019-11-10T13:51:01.359Z",
    "count": 2,
    "results": [
      {
        "Direction": "Inbound",
        "Destination": "Broombridge",
        "Time": "00:08:22",
        "AVLS": "00:09:02",
        "Tram": "5021",
        "Action": "a",
        "Msg Sent": "10/11/2019 13:50:58",
        "Msg Received": "10/11/2019 13:50:59",
        "Msg Processed": "10/11/2019 13:50:59",
        "XML ID": "9662",
        "Total Lag": "1.511649",
        "Create Lag": "1.1981717",
        "Process Lag": "0.3134773"
      },
      {
        "Direction": "Outbound",
        "Destination": "Bride's Glen",
        "Time": "00:10:51",
        "AVLS": "00:11:31",
        "Tram": "5017",
        "Action": "a",
        "Msg Sent": "10/11/2019 13:50:58",
        "Msg Received": "10/11/2019 13:50:59",
        "Msg Processed": "10/11/2019 13:50:59",
        "XML ID": "9662",
        "Total Lag": "1.4794257",
        "Create Lag": "1.1981717",
        "Process Lag": "0.281254"
      }
    ]
  },
  {
    "stopID": "34",
    "stopQueryDate": "2019-11-10T13:51:01.364Z",
    "count": 4,
    "results": [
      {
        "Direction": "Inbound",
        "Destination": "Broombridge",
        "Time": "00:00:51",
        "AVLS": "00:01:31",
        "Tram": "5011",
        "Action": "a",
        "Msg Sent": "10/11/2019 13:50:58",
        "Msg Received": "10/11/2019 13:50:59",
        "Msg Processed": "10/11/2019 13:50:59",
        "XML ID": "9662",
        "Total Lag": "1.4012997",
        "Create Lag": "1.1981717",
        "Process Lag": "0.203128"
      },
      {
        "Direction": "Inbound",
        "Destination": "Broombridge",
        "Time": "00:11:16",
        "AVLS": "00:11:56",
        "Tram": "5031",
        "Action": "a",
        "Msg Sent": "10/11/2019 13:50:51",
        "Msg Received": "10/11/2019 13:50:51",
        "Msg Processed": "10/11/2019 13:50:51",
        "XML ID": "9658",
        "Total Lag": "0.7280596",
        "Create Lag": "0.6499364",
        "Process Lag": "0.0781232"
      },
      {
        "Direction": "Outbound",
        "Destination": "Bride's Glen",
        "Time": "00:05:37",
        "AVLS": "00:06:17",
        "Tram": "5004",
        "Action": "a",
        "Msg Sent": "10/11/2019 13:50:58",
        "Msg Received": "10/11/2019 13:50:59",
        "Msg Processed": "10/11/2019 13:50:59",
        "XML ID": "9662",
        "Total Lag": "1.3075584",
        "Create Lag": "1.1981717",
        "Process Lag": "0.1093867"
      },
      {
        "Direction": "Outbound",
        "Destination": "Bride's Glen",
        "Time": "00:18:49",
        "AVLS": "00:19:29",
        "Tram": "5007",
        "Action": "a",
        "Msg Sent": "10/11/2019 13:50:58",
        "Msg Received": "10/11/2019 13:50:59",
        "Msg Processed": "10/11/2019 13:50:59",
        "XML ID": "9662",
        "Total Lag": "1.3700478",
        "Create Lag": "1.1981717",
        "Process Lag": "0.1718761"
      }
    ]
  },
  {
    "stopID": "15",
    "stopQueryDate": "2019-11-10T13:51:01.374Z",
    "count": 4,
    "results": [
      {
        "Direction": "Inbound",
        "Destination": "The Point",
        "Time": "00:08:13",
        "AVLS": "00:08:53",
        "Tram": "3023",
        "Action": "a",
        "Msg Sent": "10/11/2019 13:50:58",
        "Msg Received": "10/11/2019 13:50:58",
        "Msg Processed": "10/11/2019 13:50:58",
        "XML ID": "9661",
        "Total Lag": "0.9936926",
        "Create Lag": "0.7280626",
        "Process Lag": "0.26563"
      },
      {
        "Direction": "Inbound",
        "Destination": "The Point",
        "Time": "00:18:16",
        "AVLS": "00:18:56",
        "Tram": "3025",
        "Action": "a",
        "Msg Sent": "10/11/2019 13:50:58",
        "Msg Received": "10/11/2019 13:50:58",
        "Msg Processed": "10/11/2019 13:50:59",
        "XML ID": "9661",
        "Total Lag": "1.0419169",
        "Create Lag": "0.7280626",
        "Process Lag": "0.3138543"
      },
      {
        "Direction": "Outbound",
        "Destination": "Tallaght",
        "Time": "00:00:54",
        "AVLS": "00:01:34",
        "Tram": "3018",
        "Action": "a",
        "Msg Sent": "10/11/2019 13:50:58",
        "Msg Received": "10/11/2019 13:50:58",
        "Msg Processed": "10/11/2019 13:50:58",
        "XML ID": "9661",
        "Total Lag": "0.8999384",
        "Create Lag": "0.7280626",
        "Process Lag": "0.1718758"
      },
      {
        "Direction": "Outbound",
        "Destination": "Tallaght",
        "Time": "00:10:21",
        "AVLS": "00:11:01",
        "Tram": "3005",
        "Action": "a",
        "Msg Sent": "10/11/2019 13:50:58",
        "Msg Received": "10/11/2019 13:50:58",
        "Msg Processed": "10/11/2019 13:50:58",
        "XML ID": "9661",
        "Total Lag": "0.7437405",
        "Create Lag": "0.7280626",
        "Process Lag": "0.0156779"
      }
    ]
  },
  {
    "stopID": "38",
    "stopQueryDate": "2019-11-10T13:51:01.386Z",
    "count": 4,
    "results": [
      {
        "Direction": "Inbound",
        "Destination": "Broombridge",
        "Time": "00:03:47",
        "AVLS": "00:04:27",
        "Tram": "5031",
        "Action": "a",
        "Msg Sent": "10/11/2019 13:50:51",
        "Msg Received": "10/11/2019 13:50:51",
        "Msg Processed": "10/11/2019 13:50:51",
        "XML ID": "9658",
        "Total Lag": "0.7124416",
        "Create Lag": "0.6499364",
        "Process Lag": "0.0625052"
      },
      {
        "Direction": "Inbound",
        "Destination": "Broombridge",
        "Time": "00:16:28",
        "AVLS": "00:17:08",
        "Tram": "5021",
        "Action": "a",
        "Msg Sent": "10/11/2019 13:50:58",
        "Msg Received": "10/11/2019 13:50:59",
        "Msg Processed": "10/11/2019 13:50:59",
        "XML ID": "9662",
        "Total Lag": "1.5272901",
        "Create Lag": "1.1981717",
        "Process Lag": "0.3291184"
      },
      {
        "Direction": "Outbound",
        "Destination": "Bride's Glen",
        "Time": "00:02:52",
        "AVLS": "00:03:32",
        "Tram": "5017",
        "Action": "a",
        "Msg Sent": "10/11/2019 13:50:58",
        "Msg Received": "10/11/2019 13:50:59",
        "Msg Processed": "10/11/2019 13:50:59",
        "XML ID": "9662",
        "Total Lag": "1.4637973",
        "Create Lag": "1.1981717",
        "Process Lag": "0.2656256"
      },
      {
        "Direction": "Outbound",
        "Destination": "Bride's Glen",
        "Time": "00:12:38",
        "AVLS": "00:13:18",
        "Tram": "5004",
        "Action": "a",
        "Msg Sent": "10/11/2019 13:50:58",
        "Msg Received": "10/11/2019 13:50:59",
        "Msg Processed": "10/11/2019 13:50:59",
        "XML ID": "9662",
        "Total Lag": "1.3231783",
        "Create Lag": "1.1981717",
        "Process Lag": "0.1250066"
      }
    ]
  },
  {
    "stopID": "31",
    "stopQueryDate": "2019-11-10T13:51:01.395Z",
    "count": 4,
    "results": [
      {
        "Direction": "Inbound",
        "Destination": "Broombridge",
        "Time": "00:06:15",
        "AVLS": "00:06:55",
        "Tram": "5011",
        "Action": "a",
        "Msg Sent": "10/11/2019 13:50:58",
        "Msg Received": "10/11/2019 13:50:59",
        "Msg Processed": "10/11/2019 13:50:59",
        "XML ID": "9662",
        "Total Lag": "1.4012997",
        "Create Lag": "1.1981717",
        "Process Lag": "0.203128"
      },
      {
        "Direction": "Inbound",
        "Destination": "Broombridge",
        "Time": "00:16:40",
        "AVLS": "00:17:20",
        "Tram": "5031",
        "Action": "a",
        "Msg Sent": "10/11/2019 13:50:51",
        "Msg Received": "10/11/2019 13:50:51",
        "Msg Processed": "10/11/2019 13:50:51",
        "XML ID": "9658",
        "Total Lag": "0.7436861",
        "Create Lag": "0.6499364",
        "Process Lag": "0.0937497"
      },
      {
        "Direction": "Outbound",
        "Destination": "Bride's Glen",
        "Time": "00:00:39",
        "AVLS": "00:01:19",
        "Tram": "5004",
        "Action": "a",
        "Msg Sent": "10/11/2019 13:50:58",
        "Msg Received": "10/11/2019 13:50:59",
        "Msg Processed": "10/11/2019 13:50:59",
        "XML ID": "9662",
        "Total Lag": "1.2919341",
        "Create Lag": "1.1981717",
        "Process Lag": "0.0937624"
      },
      {
        "Direction": "Outbound",
        "Destination": "Bride's Glen",
        "Time": "00:13:51",
        "AVLS": "00:14:31",
        "Tram": "5007",
        "Action": "a",
        "Msg Sent": "10/11/2019 13:50:58",
        "Msg Received": "10/11/2019 13:50:59",
        "Msg Processed": "10/11/2019 13:50:59",
        "XML ID": "9662",
        "Total Lag": "1.3544312",
        "Create Lag": "1.1981717",
        "Process Lag": "0.1562595"
      }
    ]
  },
  {
    "stopID": "29",
    "stopQueryDate": "2019-11-10T13:51:01.400Z",
    "count": 3,
    "results": [
      {
        "Direction": "Inbound",
        "Destination": "Broombridge",
        "Time": "00:00:00",
        "AVLS": "00:00:00",
        "Tram": "5003",
        "Action": "a",
        "Msg Sent": "10/11/2019 13:50:40",
        "Msg Received": "10/11/2019 13:50:40",
        "Msg Processed": "10/11/2019 13:50:40",
        "XML ID": "9653",
        "Total Lag": "0.5249375",
        "Create Lag": "0.3218095",
        "Process Lag": "0.203128"
      },
      {
        "Direction": "Inbound",
        "Destination": "Broombridge",
        "Time": "00:09:47",
        "AVLS": "00:10:27",
        "Tram": "5011",
        "Action": "a",
        "Msg Sent": "10/11/2019 13:50:58",
        "Msg Received": "10/11/2019 13:50:59",
        "Msg Processed": "10/11/2019 13:50:59",
        "XML ID": "9662",
        "Total Lag": "1.4012997",
        "Create Lag": "1.1981717",
        "Process Lag": "0.203128"
      },
      {
        "Direction": "Outbound",
        "Destination": "Bride's Glen",
        "Time": "00:10:17",
        "AVLS": "00:10:57",
        "Tram": "5007",
        "Action": "a",
        "Msg Sent": "10/11/2019 13:50:58",
        "Msg Received": "10/11/2019 13:50:59",
        "Msg Processed": "10/11/2019 13:50:59",
        "XML ID": "9662",
        "Total Lag": "1.3544312",
        "Create Lag": "1.1981717",
        "Process Lag": "0.1562595"
      }
    ]
  },
  {
    "stopID": "48",
    "stopQueryDate": "2019-11-10T13:51:01.408Z",
    "count": 2,
    "results": [
      {
        "Direction": "Inbound",
        "Destination": "Broombridge",
        "Time": "00:02:22",
        "AVLS": "00:03:02",
        "Tram": "5021",
        "Action": "d",
        "Msg Sent": "10/11/2019 13:50:58",
        "Msg Received": "10/11/2019 13:50:59",
        "Msg Processed": "10/11/2019 13:50:59",
        "XML ID": "9662",
        "Total Lag": "1.4973701",
        "Create Lag": "1.1981717",
        "Process Lag": "0.2991984"
      },
      {
        "Direction": "Inbound",
        "Destination": "Broombridge",
        "Time": "00:14:22",
        "AVLS": "00:15:02",
        "Tram": "5015",
        "Action": "d",
        "Msg Sent": "10/11/2019 13:50:58",
        "Msg Received": "10/11/2019 13:50:59",
        "Msg Processed": "10/11/2019 13:50:59",
        "XML ID": "9662",
        "Total Lag": "1.4325589",
        "Create Lag": "1.1981717",
        "Process Lag": "0.2343872"
      }
    ]
  },
  {
    "stopID": "19",
    "stopQueryDate": "2019-11-10T13:51:01.418Z",
    "count": 4,
    "results": [
      {
        "Direction": "Inbound",
        "Destination": "The Point",
        "Time": "00:08:10",
        "AVLS": "00:08:50",
        "Tram": "4005",
        "Action": "a",
        "Msg Sent": "10/11/2019 13:50:58",
        "Msg Received": "10/11/2019 13:50:59",
        "Msg Processed": "10/11/2019 13:50:59",
        "XML ID": "9662",
        "Total Lag": "1.2137973",
        "Create Lag": "1.1981717",
        "Process Lag": "0.0156256"
      },
      {
        "Direction": "Inbound",
        "Destination": "The Point",
        "Time": "00:17:32",
        "AVLS": "00:18:12",
        "Tram": "3023",
        "Action": "a",
        "Msg Sent": "10/11/2019 13:50:58",
        "Msg Received": "10/11/2019 13:50:58",
        "Msg Processed": "10/11/2019 13:50:59",
        "XML ID": "9661",
        "Total Lag": "1.0093174",
        "Create Lag": "0.7280626",
        "Process Lag": "0.2812548"
      },
      {
        "Direction": "Outbound",
        "Destination": "Tallaght",
        "Time": "00:01:12",
        "AVLS": "00:01:52",
        "Tram": "3005",
        "Action": "a",
        "Msg Sent": "10/11/2019 13:50:58",
        "Msg Received": "10/11/2019 13:50:58",
        "Msg Processed": "10/11/2019 13:50:58",
        "XML ID": "9661",
        "Total Lag": "0.7280626",
        "Create Lag": "0.7280626",
        "Process Lag": "0"
      },
      {
        "Direction": "Outbound",
        "Destination": "Tallaght",
        "Time": "00:10:41",
        "AVLS": "00:11:21",
        "Tram": "4002",
        "Action": "a",
        "Msg Sent": "10/11/2019 13:50:58",
        "Msg Received": "10/11/2019 13:50:58",
        "Msg Processed": "10/11/2019 13:50:59",
        "XML ID": "9661",
        "Total Lag": "1.0731743",
        "Create Lag": "0.7280626",
        "Process Lag": "0.3451117"
      }
    ]
  },
  {
    "stopID": "33",
    "stopQueryDate": "2019-11-10T13:51:01.428Z",
    "count": 4,
    "results": [
      {
        "Direction": "Inbound",
        "Destination": "Broombridge",
        "Time": "00:02:34",
        "AVLS": "00:03:14",
        "Tram": "5011",
        "Action": "a",
        "Msg Sent": "10/11/2019 13:50:58",
        "Msg Received": "10/11/2019 13:50:59",
        "Msg Processed": "10/11/2019 13:50:59",
        "XML ID": "9662",
        "Total Lag": "1.4012997",
        "Create Lag": "1.1981717",
        "Process Lag": "0.203128"
      },
      {
        "Direction": "Inbound",
        "Destination": "Broombridge",
        "Time": "00:12:59",
        "AVLS": "00:13:39",
        "Tram": "5031",
        "Action": "a",
        "Msg Sent": "10/11/2019 13:50:51",
        "Msg Received": "10/11/2019 13:50:51",
        "Msg Processed": "10/11/2019 13:50:51",
        "XML ID": "9658",
        "Total Lag": "0.7280596",
        "Create Lag": "0.6499364",
        "Process Lag": "0.0781232"
      },
      {
        "Direction": "Outbound",
        "Destination": "Bride's Glen",
        "Time": "00:04:03",
        "AVLS": "00:04:43",
        "Tram": "5004",
        "Action": "a",
        "Msg Sent": "10/11/2019 13:50:58",
        "Msg Received": "10/11/2019 13:50:59",
        "Msg Processed": "10/11/2019 13:50:59",
        "XML ID": "9662",
        "Total Lag": "1.3075584",
        "Create Lag": "1.1981717",
        "Process Lag": "0.1093867"
      },
      {
        "Direction": "Outbound",
        "Destination": "Bride's Glen",
        "Time": "00:17:15",
        "AVLS": "00:17:55",
        "Tram": "5007",
        "Action": "a",
        "Msg Sent": "10/11/2019 13:50:58",
        "Msg Received": "10/11/2019 13:50:59",
        "Msg Processed": "10/11/2019 13:50:59",
        "XML ID": "9662",
        "Total Lag": "1.3700478",
        "Create Lag": "1.1981717",
        "Process Lag": "0.1718761"
      }
    ]
  },
  {
    "stopID": "37",
    "stopQueryDate": "2019-11-10T13:51:01.439Z",
    "count": 4,
    "results": [
      {
        "Direction": "Inbound",
        "Destination": "Broombridge",
        "Time": "00:05:17",
        "AVLS": "00:05:57",
        "Tram": "5031",
        "Action": "a",
        "Msg Sent": "10/11/2019 13:50:51",
        "Msg Received": "10/11/2019 13:50:51",
        "Msg Processed": "10/11/2019 13:50:51",
        "XML ID": "9658",
        "Total Lag": "0.7280596",
        "Create Lag": "0.6499364",
        "Process Lag": "0.0781232"
      },
      {
        "Direction": "Inbound",
        "Destination": "Broombridge",
        "Time": "00:17:58",
        "AVLS": "00:18:38",
        "Tram": "5021",
        "Action": "a",
        "Msg Sent": "10/11/2019 13:50:58",
        "Msg Received": "10/11/2019 13:50:59",
        "Msg Processed": "10/11/2019 13:50:59",
        "XML ID": "9662",
        "Total Lag": "1.5272901",
        "Create Lag": "1.1981717",
        "Process Lag": "0.3291184"
      },
      {
        "Direction": "Outbound",
        "Destination": "Bride's Glen",
        "Time": "00:01:24",
        "AVLS": "00:02:04",
        "Tram": "5017",
        "Action": "a",
        "Msg Sent": "10/11/2019 13:50:58",
        "Msg Received": "10/11/2019 13:50:59",
        "Msg Processed": "10/11/2019 13:50:59",
        "XML ID": "9662",
        "Total Lag": "1.4481832",
        "Create Lag": "1.1981717",
        "Process Lag": "0.2500115"
      },
      {
        "Direction": "Outbound",
        "Destination": "Bride's Glen",
        "Time": "00:11:10",
        "AVLS": "00:11:50",
        "Tram": "5004",
        "Action": "a",
        "Msg Sent": "10/11/2019 13:50:58",
        "Msg Received": "10/11/2019 13:50:59",
        "Msg Processed": "10/11/2019 13:50:59",
        "XML ID": "9662",
        "Total Lag": "1.3231783",
        "Create Lag": "1.1981717",
        "Process Lag": "0.1250066"
      }
    ]
  },
  {
    "stopID": "55",
    "stopQueryDate": "2019-11-10T13:51:01.446Z",
    "count": 2,
    "results": [
      {
        "Direction": "Inbound",
        "Destination": "The Point",
        "Time": "00:07:54",
        "AVLS": "00:08:34",
        "Tram": "3006",
        "Action": "a",
        "Msg Sent": "10/11/2019 13:50:58",
        "Msg Received": "10/11/2019 13:50:58",
        "Msg Processed": "10/11/2019 13:50:58",
        "XML ID": "9661",
        "Total Lag": "0.774944",
        "Create Lag": "0.7280626",
        "Process Lag": "0.0468814"
      },
      {
        "Direction": "Outbound",
        "Destination": "Tallaght",
        "Time": "00:09:30",
        "AVLS": "00:10:10",
        "Tram": "3011",
        "Action": "a",
        "Msg Sent": "10/11/2019 13:50:58",
        "Msg Received": "10/11/2019 13:50:58",
        "Msg Processed": "10/11/2019 13:50:58",
        "XML ID": "9661",
        "Total Lag": "0.8061905",
        "Create Lag": "0.7280626",
        "Process Lag": "0.0781279"
      }
    ]
  },
  {
    "stopID": "21",
    "stopQueryDate": "2019-11-10T13:51:01.451Z",
    "count": 4,
    "results": [
      {
        "Direction": "Inbound",
        "Destination": "The Point",
        "Time": "00:01:40",
        "AVLS": "00:02:20",
        "Tram": "3006",
        "Action": "a",
        "Msg Sent": "10/11/2019 13:50:58",
        "Msg Received": "10/11/2019 13:50:58",
        "Msg Processed": "10/11/2019 13:50:58",
        "XML ID": "9661",
        "Total Lag": "0.774944",
        "Create Lag": "0.7280626",
        "Process Lag": "0.0468814"
      },
      {
        "Direction": "Inbound",
        "Destination": "The Point",
        "Time": "00:13:33",
        "AVLS": "00:14:13",
        "Tram": "4005",
        "Action": "a",
        "Msg Sent": "10/11/2019 13:50:58",
        "Msg Received": "10/11/2019 13:50:59",
        "Msg Processed": "10/11/2019 13:50:59",
        "XML ID": "9662",
        "Total Lag": "1.2137973",
        "Create Lag": "1.1981717",
        "Process Lag": "0.0156256"
      },
      {
        "Direction": "Outbound",
        "Destination": "Tallaght",
        "Time": "00:05:39",
        "AVLS": "00:06:19",
        "Tram": "4002",
        "Action": "a",
        "Msg Sent": "10/11/2019 13:50:58",
        "Msg Received": "10/11/2019 13:50:58",
        "Msg Processed": "10/11/2019 13:50:59",
        "XML ID": "9661",
        "Total Lag": "1.0731743",
        "Create Lag": "0.7280626",
        "Process Lag": "0.3451117"
      },
      {
        "Direction": "Outbound",
        "Destination": "Tallaght",
        "Time": "00:16:22",
        "AVLS": "00:17:02",
        "Tram": "3011",
        "Action": "a",
        "Msg Sent": "10/11/2019 13:50:58",
        "Msg Received": "10/11/2019 13:50:58",
        "Msg Processed": "10/11/2019 13:50:58",
        "XML ID": "9661",
        "Total Lag": "0.8218179",
        "Create Lag": "0.7280626",
        "Process Lag": "0.0937553"
      }
    ]
  },
  {
    "stopID": "40",
    "stopQueryDate": "2019-11-10T13:51:01.465Z",
    "count": 4,
    "results": [
      {
        "Direction": "Inbound",
        "Destination": "Broombridge",
        "Time": "00:00:32",
        "AVLS": "00:01:12",
        "Tram": "5031",
        "Action": "a",
        "Msg Sent": "10/11/2019 13:50:51",
        "Msg Received": "10/11/2019 13:50:51",
        "Msg Processed": "10/11/2019 13:50:51",
        "XML ID": "9658",
        "Total Lag": "0.7124416",
        "Create Lag": "0.6499364",
        "Process Lag": "0.0625052"
      },
      {
        "Direction": "Inbound",
        "Destination": "Broombridge",
        "Time": "00:13:13",
        "AVLS": "00:13:53",
        "Tram": "5021",
        "Action": "a",
        "Msg Sent": "10/11/2019 13:50:58",
        "Msg Received": "10/11/2019 13:50:59",
        "Msg Processed": "10/11/2019 13:50:59",
        "XML ID": "9662",
        "Total Lag": "1.5272901",
        "Create Lag": "1.1981717",
        "Process Lag": "0.3291184"
      },
      {
        "Direction": "Outbound",
        "Destination": "Bride's Glen",
        "Time": "00:06:05",
        "AVLS": "00:06:45",
        "Tram": "5017",
        "Action": "a",
        "Msg Sent": "10/11/2019 13:50:58",
        "Msg Received": "10/11/2019 13:50:59",
        "Msg Processed": "10/11/2019 13:50:59",
        "XML ID": "9662",
        "Total Lag": "1.4637973",
        "Create Lag": "1.1981717",
        "Process Lag": "0.2656256"
      },
      {
        "Direction": "Outbound",
        "Destination": "Bride's Glen",
        "Time": "00:15:51",
        "AVLS": "00:16:31",
        "Tram": "5004",
        "Action": "a",
        "Msg Sent": "10/11/2019 13:50:58",
        "Msg Received": "10/11/2019 13:50:59",
        "Msg Processed": "10/11/2019 13:50:59",
        "XML ID": "9662",
        "Total Lag": "1.3231783",
        "Create Lag": "1.1981717",
        "Process Lag": "0.1250066"
      }
    ]
  },
  {
    "stopID": "24",
    "stopQueryDate": "2019-11-10T13:51:01.476Z",
    "count": 4,
    "results": [
      {
        "Direction": "Inbound",
        "Destination": "Broombridge",
        "Time": "00:08:30",
        "AVLS": "00:09:10",
        "Tram": "5003",
        "Action": "a",
        "Msg Sent": "10/11/2019 13:50:58",
        "Msg Received": "10/11/2019 13:50:59",
        "Msg Processed": "10/11/2019 13:50:59",
        "XML ID": "9662",
        "Total Lag": "1.2607258",
        "Create Lag": "1.1981717",
        "Process Lag": "0.0625541"
      },
      {
        "Direction": "Inbound",
        "Destination": "Broombridge",
        "Time": "00:19:16",
        "AVLS": "00:19:56",
        "Tram": "5011",
        "Action": "a",
        "Msg Sent": "10/11/2019 13:50:58",
        "Msg Received": "10/11/2019 13:50:59",
        "Msg Processed": "10/11/2019 13:50:59",
        "XML ID": "9662",
        "Total Lag": "1.4169378",
        "Create Lag": "1.1981717",
        "Process Lag": "0.2187661"
      },
      {
        "Direction": "Outbound",
        "Destination": "Bride's Glen",
        "Time": "00:00:49",
        "AVLS": "00:01:29",
        "Tram": "5007",
        "Action": "a",
        "Msg Sent": "10/11/2019 13:50:58",
        "Msg Received": "10/11/2019 13:50:59",
        "Msg Processed": "10/11/2019 13:50:59",
        "XML ID": "9662",
        "Total Lag": "1.3387994",
        "Create Lag": "1.1981717",
        "Process Lag": "0.1406277"
      },
      {
        "Direction": "Outbound",
        "Destination": "Bride's Glen",
        "Time": "00:11:40",
        "AVLS": "00:12:20",
        "Tram": "5008",
        "Action": "a",
        "Msg Sent": "10/11/2019 13:50:58",
        "Msg Received": "10/11/2019 13:50:59",
        "Msg Processed": "10/11/2019 13:50:59",
        "XML ID": "9662",
        "Total Lag": "1.3856764",
        "Create Lag": "1.1981717",
        "Process Lag": "0.1875047"
      }
    ]
  },
  {
    "stopID": "17",
    "stopQueryDate": "2019-11-10T13:51:01.486Z",
    "count": 4,
    "results": [
      {
        "Direction": "Inbound",
        "Destination": "The Point",
        "Time": "00:04:10",
        "AVLS": "00:04:50",
        "Tram": "4005",
        "Action": "a",
        "Msg Sent": "10/11/2019 13:50:58",
        "Msg Received": "10/11/2019 13:50:59",
        "Msg Processed": "10/11/2019 13:50:59",
        "XML ID": "9662",
        "Total Lag": "1.2137973",
        "Create Lag": "1.1981717",
        "Process Lag": "0.0156256"
      },
      {
        "Direction": "Inbound",
        "Destination": "The Point",
        "Time": "00:13:32",
        "AVLS": "00:14:12",
        "Tram": "3023",
        "Action": "a",
        "Msg Sent": "10/11/2019 13:50:58",
        "Msg Received": "10/11/2019 13:50:58",
        "Msg Processed": "10/11/2019 13:50:58",
        "XML ID": "9661",
        "Total Lag": "0.9936926",
        "Create Lag": "0.7280626",
        "Process Lag": "0.26563"
      },
      {
        "Direction": "Outbound",
        "Destination": "Tallaght",
        "Time": "00:04:57",
        "AVLS": "00:05:37",
        "Tram": "3005",
        "Action": "a",
        "Msg Sent": "10/11/2019 13:50:58",
        "Msg Received": "10/11/2019 13:50:58",
        "Msg Processed": "10/11/2019 13:50:58",
        "XML ID": "9661",
        "Total Lag": "0.7437405",
        "Create Lag": "0.7280626",
        "Process Lag": "0.0156779"
      },
      {
        "Direction": "Outbound",
        "Destination": "Tallaght",
        "Time": "00:14:26",
        "AVLS": "00:15:06",
        "Tram": "4002",
        "Action": "a",
        "Msg Sent": "10/11/2019 13:50:58",
        "Msg Received": "10/11/2019 13:50:59",
        "Msg Processed": "10/11/2019 13:50:59",
        "XML ID": "9662",
        "Total Lag": "1.1981717",
        "Create Lag": "1.1981717",
        "Process Lag": "0"
      }
    ]
  },
  {
    "stopID": "51",
    "stopQueryDate": "2019-11-10T13:51:01.497Z",
    "count": 3,
    "results": [
      {
        "Direction": "Inbound",
        "Destination": "Belgard",
        "Time": "00:07:53",
        "AVLS": "00:08:33",
        "Tram": "4013",
        "Action": "a",
        "Msg Sent": "10/11/2019 13:50:58",
        "Msg Received": "10/11/2019 13:50:59",
        "Msg Processed": "10/11/2019 13:50:59",
        "XML ID": "9662",
        "Total Lag": "1.2450509",
        "Create Lag": "1.1981717",
        "Process Lag": "0.0468792"
      },
      {
        "Direction": "Inbound",
        "Destination": "Belgard",
        "Time": "00:18:53",
        "AVLS": "00:19:33",
        "Tram": "3019",
        "Action": "a",
        "Msg Sent": "10/11/2019 13:50:58",
        "Msg Received": "10/11/2019 13:50:58",
        "Msg Processed": "10/11/2019 13:50:58",
        "XML ID": "9661",
        "Total Lag": "0.9468228",
        "Create Lag": "0.7280626",
        "Process Lag": "0.2187602"
      },
      {
        "Direction": "Outbound",
        "Destination": "Saggart",
        "Time": "00:09:52",
        "AVLS": "00:10:32",
        "Tram": "3026",
        "Action": "a",
        "Msg Sent": "10/11/2019 13:50:58",
        "Msg Received": "10/11/2019 13:50:58",
        "Msg Processed": "10/11/2019 13:50:59",
        "XML ID": "9661",
        "Total Lag": "1.0419169",
        "Create Lag": "0.7280626",
        "Process Lag": "0.3138543"
      }
    ]
  },
  {
    "stopID": "30",
    "stopQueryDate": "2019-11-10T13:51:01.506Z",
    "count": 4,
    "results": [
      {
        "Direction": "Inbound",
        "Destination": "Broombridge",
        "Time": "00:08:02",
        "AVLS": "00:08:42",
        "Tram": "5011",
        "Action": "a",
        "Msg Sent": "10/11/2019 13:50:58",
        "Msg Received": "10/11/2019 13:50:59",
        "Msg Processed": "10/11/2019 13:50:59",
        "XML ID": "9662",
        "Total Lag": "1.4012997",
        "Create Lag": "1.1981717",
        "Process Lag": "0.203128"
      },
      {
        "Direction": "Inbound",
        "Destination": "Broombridge",
        "Time": "00:18:27",
        "AVLS": "00:19:07",
        "Tram": "5031",
        "Action": "a",
        "Msg Sent": "10/11/2019 13:50:51",
        "Msg Received": "10/11/2019 13:50:51",
        "Msg Processed": "10/11/2019 13:50:51",
        "XML ID": "9658",
        "Total Lag": "0.7436861",
        "Create Lag": "0.6499364",
        "Process Lag": "0.0937497"
      },
      {
        "Direction": "Outbound",
        "Destination": "Bride's Glen",
        "Time": "00:00:00",
        "AVLS": "00:00:00",
        "Tram": "5004",
        "Action": "a",
        "Msg Sent": "10/11/2019 13:50:31",
        "Msg Received": "10/11/2019 13:50:31",
        "Msg Processed": "10/11/2019 13:50:31",
        "XML ID": "9649",
        "Total Lag": "0.5783041",
        "Create Lag": "0.5001695",
        "Process Lag": "0.0781346"
      },
      {
        "Direction": "Outbound",
        "Destination": "Bride's Glen",
        "Time": "00:12:03",
        "AVLS": "00:12:43",
        "Tram": "5007",
        "Action": "a",
        "Msg Sent": "10/11/2019 13:50:58",
        "Msg Received": "10/11/2019 13:50:59",
        "Msg Processed": "10/11/2019 13:50:59",
        "XML ID": "9662",
        "Total Lag": "1.3544312",
        "Create Lag": "1.1981717",
        "Process Lag": "0.1562595"
      }
    ]
  },
  {
    "stopID": "47",
    "stopQueryDate": "2019-11-10T13:51:01.510Z",
    "count": 4,
    "results": [
      {
        "Direction": "Inbound",
        "Destination": "Broombridge",
        "Time": "00:03:30",
        "AVLS": "00:04:10",
        "Tram": "5021",
        "Action": "a",
        "Msg Sent": "10/11/2019 13:50:58",
        "Msg Received": "10/11/2019 13:50:59",
        "Msg Processed": "10/11/2019 13:50:59",
        "XML ID": "9662",
        "Total Lag": "1.4973701",
        "Create Lag": "1.1981717",
        "Process Lag": "0.2991984"
      },
      {
        "Direction": "Inbound",
        "Destination": "Broombridge",
        "Time": "00:15:30",
        "AVLS": "00:16:10",
        "Tram": "5015",
        "Action": "a",
        "Msg Sent": "10/11/2019 13:50:58",
        "Msg Received": "10/11/2019 13:50:59",
        "Msg Processed": "10/11/2019 13:50:59",
        "XML ID": "9662",
        "Total Lag": "1.4325589",
        "Create Lag": "1.1981717",
        "Process Lag": "0.2343872"
      },
      {
        "Direction": "Outbound",
        "Destination": "Bride's Glen",
        "Time": "00:02:32",
        "AVLS": "00:03:12",
        "Tram": "5015",
        "Action": "a",
        "Msg Sent": "10/11/2019 13:50:58",
        "Msg Received": "10/11/2019 13:50:59",
        "Msg Processed": "10/11/2019 13:50:59",
        "XML ID": "9662",
        "Total Lag": "1.4325589",
        "Create Lag": "1.1981717",
        "Process Lag": "0.2343872"
      },
      {
        "Direction": "Outbound",
        "Destination": "Bride's Glen",
        "Time": "00:15:39",
        "AVLS": "00:16:19",
        "Tram": "5017",
        "Action": "a",
        "Msg Sent": "10/11/2019 13:50:58",
        "Msg Received": "10/11/2019 13:50:59",
        "Msg Processed": "10/11/2019 13:50:59",
        "XML ID": "9662",
        "Total Lag": "1.4973701",
        "Create Lag": "1.1981717",
        "Process Lag": "0.2991984"
      }
    ]
  },
  {
    "stopID": "56",
    "stopQueryDate": "2019-11-10T13:51:01.519Z",
    "count": 3,
    "results": [
      {
        "Direction": "Inbound",
        "Destination": "The Point",
        "Time": "00:09:33",
        "AVLS": "00:10:13",
        "Tram": "3006",
        "Action": "a",
        "Msg Sent": "10/11/2019 13:50:58",
        "Msg Received": "10/11/2019 13:50:58",
        "Msg Processed": "10/11/2019 13:50:58",
        "XML ID": "9661",
        "Total Lag": "0.7906099",
        "Create Lag": "0.7280626",
        "Process Lag": "0.0625473"
      },
      {
        "Direction": "Outbound",
        "Destination": "Tallaght",
        "Time": "00:07:31",
        "AVLS": "00:08:11",
        "Tram": "3011",
        "Action": "a",
        "Msg Sent": "10/11/2019 13:50:58",
        "Msg Received": "10/11/2019 13:50:58",
        "Msg Processed": "10/11/2019 13:50:58",
        "XML ID": "9661",
        "Total Lag": "0.7906099",
        "Create Lag": "0.7280626",
        "Process Lag": "0.0625473"
      },
      {
        "Direction": "Outbound",
        "Destination": "Tallaght",
        "Time": "00:18:31",
        "AVLS": "00:19:11",
        "Tram": "3006",
        "Action": "a",
        "Msg Sent": "10/11/2019 13:50:58",
        "Msg Received": "10/11/2019 13:50:58",
        "Msg Processed": "10/11/2019 13:50:58",
        "XML ID": "9661",
        "Total Lag": "0.7906099",
        "Create Lag": "0.7280626",
        "Process Lag": "0.0625473"
      }
    ]
  },
  {
    "stopID": "49",
    "stopQueryDate": "2019-11-10T13:51:01.527Z",
    "count": 4,
    "results": [
      {
        "Direction": "Inbound",
        "Destination": "Belgard",
        "Time": "00:01:25",
        "AVLS": "00:02:05",
        "Tram": "3014",
        "Action": "a",
        "Msg Sent": "10/11/2019 13:50:58",
        "Msg Received": "10/11/2019 13:50:58",
        "Msg Processed": "10/11/2019 13:50:58",
        "XML ID": "9661",
        "Total Lag": "0.8218179",
        "Create Lag": "0.7280626",
        "Process Lag": "0.0937553"
      },
      {
        "Direction": "Inbound",
        "Destination": "Belgard",
        "Time": "00:11:28",
        "AVLS": "00:12:08",
        "Tram": "4013",
        "Action": "a",
        "Msg Sent": "10/11/2019 13:50:58",
        "Msg Received": "10/11/2019 13:50:59",
        "Msg Processed": "10/11/2019 13:50:59",
        "XML ID": "9662",
        "Total Lag": "1.2450509",
        "Create Lag": "1.1981717",
        "Process Lag": "0.0468792"
      },
      {
        "Direction": "Outbound",
        "Destination": "Saggart",
        "Time": "00:06:19",
        "AVLS": "00:06:59",
        "Tram": "3026",
        "Action": "a",
        "Msg Sent": "10/11/2019 13:50:58",
        "Msg Received": "10/11/2019 13:50:58",
        "Msg Processed": "10/11/2019 13:50:59",
        "XML ID": "9661",
        "Total Lag": "1.0419169",
        "Create Lag": "0.7280626",
        "Process Lag": "0.3138543"
      },
      {
        "Direction": "Outbound",
        "Destination": "Saggart",
        "Time": "00:16:19",
        "AVLS": "00:16:59",
        "Tram": "3014",
        "Action": "a",
        "Msg Sent": "10/11/2019 13:50:58",
        "Msg Received": "10/11/2019 13:50:58",
        "Msg Processed": "10/11/2019 13:50:58",
        "XML ID": "9661",
        "Total Lag": "0.837442",
        "Create Lag": "0.7280626",
        "Process Lag": "0.1093794"
      }
    ]
  },
  {
    "stopID": "27",
    "stopQueryDate": "2019-11-10T13:51:01.535Z",
    "count": 4,
    "results": [
      {
        "Direction": "Inbound",
        "Destination": "Broombridge",
        "Time": "00:02:01",
        "AVLS": "00:02:41",
        "Tram": "5003",
        "Action": "a",
        "Msg Sent": "10/11/2019 13:50:58",
        "Msg Received": "10/11/2019 13:50:59",
        "Msg Processed": "10/11/2019 13:50:59",
        "XML ID": "9662",
        "Total Lag": "1.2607258",
        "Create Lag": "1.1981717",
        "Process Lag": "0.0625541"
      },
      {
        "Direction": "Inbound",
        "Destination": "Broombridge",
        "Time": "00:12:47",
        "AVLS": "00:13:27",
        "Tram": "5011",
        "Action": "a",
        "Msg Sent": "10/11/2019 13:50:58",
        "Msg Received": "10/11/2019 13:50:59",
        "Msg Processed": "10/11/2019 13:50:59",
        "XML ID": "9662",
        "Total Lag": "1.4169378",
        "Create Lag": "1.1981717",
        "Process Lag": "0.2187661"
      },
      {
        "Direction": "Outbound",
        "Destination": "Bride's Glen",
        "Time": "00:06:55",
        "AVLS": "00:07:35",
        "Tram": "5007",
        "Action": "a",
        "Msg Sent": "10/11/2019 13:50:58",
        "Msg Received": "10/11/2019 13:50:59",
        "Msg Processed": "10/11/2019 13:50:59",
        "XML ID": "9662",
        "Total Lag": "1.3387994",
        "Create Lag": "1.1981717",
        "Process Lag": "0.1406277"
      },
      {
        "Direction": "Outbound",
        "Destination": "Bride's Glen",
        "Time": "00:17:46",
        "AVLS": "00:18:26",
        "Tram": "5008",
        "Action": "a",
        "Msg Sent": "10/11/2019 13:50:58",
        "Msg Received": "10/11/2019 13:50:59",
        "Msg Processed": "10/11/2019 13:50:59",
        "XML ID": "9662",
        "Total Lag": "1.3856764",
        "Create Lag": "1.1981717",
        "Process Lag": "0.1875047"
      }
    ]
  },
  {
    "stopID": "57",
    "stopQueryDate": "2019-11-10T13:51:01.544Z",
    "count": 2,
    "results": [
      {
        "Direction": "Outbound",
        "Destination": "Tallaght",
        "Time": "00:06:52",
        "AVLS": "00:07:32",
        "Tram": "3011",
        "Action": "d",
        "Msg Sent": "10/11/2019 13:50:58",
        "Msg Received": "10/11/2019 13:50:58",
        "Msg Processed": "10/11/2019 13:50:58",
        "XML ID": "9661",
        "Total Lag": "0.7906099",
        "Create Lag": "0.7280626",
        "Process Lag": "0.0625473"
      },
      {
        "Direction": "Outbound",
        "Destination": "Tallaght",
        "Time": "00:17:52",
        "AVLS": "00:18:32",
        "Tram": "3006",
        "Action": "d",
        "Msg Sent": "10/11/2019 13:50:58",
        "Msg Received": "10/11/2019 13:50:58",
        "Msg Processed": "10/11/2019 13:50:58",
        "XML ID": "9661",
        "Total Lag": "0.7906099",
        "Create Lag": "0.7280626",
        "Process Lag": "0.0625473"
      }
    ]
  },
  {
    "stopID": "32",
    "stopQueryDate": "2019-11-10T13:51:01.549Z",
    "count": 4,
    "results": [
      {
        "Direction": "Inbound",
        "Destination": "Broombridge",
        "Time": "00:04:16",
        "AVLS": "00:04:56",
        "Tram": "5011",
        "Action": "a",
        "Msg Sent": "10/11/2019 13:50:58",
        "Msg Received": "10/11/2019 13:50:59",
        "Msg Processed": "10/11/2019 13:50:59",
        "XML ID": "9662",
        "Total Lag": "1.4012997",
        "Create Lag": "1.1981717",
        "Process Lag": "0.203128"
      },
      {
        "Direction": "Inbound",
        "Destination": "Broombridge",
        "Time": "00:14:41",
        "AVLS": "00:15:21",
        "Tram": "5031",
        "Action": "a",
        "Msg Sent": "10/11/2019 13:50:51",
        "Msg Received": "10/11/2019 13:50:51",
        "Msg Processed": "10/11/2019 13:50:51",
        "XML ID": "9658",
        "Total Lag": "0.7280596",
        "Create Lag": "0.6499364",
        "Process Lag": "0.0781232"
      },
      {
        "Direction": "Outbound",
        "Destination": "Bride's Glen",
        "Time": "00:02:37",
        "AVLS": "00:03:17",
        "Tram": "5004",
        "Action": "a",
        "Msg Sent": "10/11/2019 13:50:58",
        "Msg Received": "10/11/2019 13:50:59",
        "Msg Processed": "10/11/2019 13:50:59",
        "XML ID": "9662",
        "Total Lag": "1.2919341",
        "Create Lag": "1.1981717",
        "Process Lag": "0.0937624"
      },
      {
        "Direction": "Outbound",
        "Destination": "Bride's Glen",
        "Time": "00:15:49",
        "AVLS": "00:16:29",
        "Tram": "5007",
        "Action": "a",
        "Msg Sent": "10/11/2019 13:50:58",
        "Msg Received": "10/11/2019 13:50:59",
        "Msg Processed": "10/11/2019 13:50:59",
        "XML ID": "9662",
        "Total Lag": "1.3544312",
        "Create Lag": "1.1981717",
        "Process Lag": "0.1562595"
      }
    ]
  },
  {
    "stopID": "50",
    "stopQueryDate": "2019-11-10T13:51:01.558Z",
    "count": 4,
    "results": [
      {
        "Direction": "Inbound",
        "Destination": "Belgard",
        "Time": "00:00:00",
        "AVLS": "00:00:17",
        "Tram": "3014",
        "Action": "a",
        "Msg Sent": "10/11/2019 13:50:58",
        "Msg Received": "10/11/2019 13:50:58",
        "Msg Processed": "10/11/2019 13:50:58",
        "XML ID": "9661",
        "Total Lag": "0.8218179",
        "Create Lag": "0.7280626",
        "Process Lag": "0.0937553"
      },
      {
        "Direction": "Inbound",
        "Destination": "Belgard",
        "Time": "00:09:40",
        "AVLS": "00:10:20",
        "Tram": "4013",
        "Action": "a",
        "Msg Sent": "10/11/2019 13:50:58",
        "Msg Received": "10/11/2019 13:50:59",
        "Msg Processed": "10/11/2019 13:50:59",
        "XML ID": "9662",
        "Total Lag": "1.2450509",
        "Create Lag": "1.1981717",
        "Process Lag": "0.0468792"
      },
      {
        "Direction": "Outbound",
        "Destination": "Saggart",
        "Time": "00:08:05",
        "AVLS": "00:08:45",
        "Tram": "3026",
        "Action": "a",
        "Msg Sent": "10/11/2019 13:50:58",
        "Msg Received": "10/11/2019 13:50:58",
        "Msg Processed": "10/11/2019 13:50:59",
        "XML ID": "9661",
        "Total Lag": "1.0419169",
        "Create Lag": "0.7280626",
        "Process Lag": "0.3138543"
      },
      {
        "Direction": "Outbound",
        "Destination": "Saggart",
        "Time": "00:18:05",
        "AVLS": "00:18:45",
        "Tram": "3014",
        "Action": "a",
        "Msg Sent": "10/11/2019 13:50:58",
        "Msg Received": "10/11/2019 13:50:58",
        "Msg Processed": "10/11/2019 13:50:58",
        "XML ID": "9661",
        "Total Lag": "0.837442",
        "Create Lag": "0.7280626",
        "Process Lag": "0.1093794"
      }
    ]
  },
  {
    "stopID": "26",
    "stopQueryDate": "2019-11-10T13:51:01.566Z",
    "count": 4,
    "results": [
      {
        "Direction": "Inbound",
        "Destination": "Broombridge",
        "Time": "00:03:22",
        "AVLS": "00:04:02",
        "Tram": "5003",
        "Action": "a",
        "Msg Sent": "10/11/2019 13:50:58",
        "Msg Received": "10/11/2019 13:50:59",
        "Msg Processed": "10/11/2019 13:50:59",
        "XML ID": "9662",
        "Total Lag": "1.2607258",
        "Create Lag": "1.1981717",
        "Process Lag": "0.0625541"
      },
      {
        "Direction": "Inbound",
        "Destination": "Broombridge",
        "Time": "00:14:08",
        "AVLS": "00:14:48",
        "Tram": "5011",
        "Action": "a",
        "Msg Sent": "10/11/2019 13:50:58",
        "Msg Received": "10/11/2019 13:50:59",
        "Msg Processed": "10/11/2019 13:50:59",
        "XML ID": "9662",
        "Total Lag": "1.4169378",
        "Create Lag": "1.1981717",
        "Process Lag": "0.2187661"
      },
      {
        "Direction": "Outbound",
        "Destination": "Bride's Glen",
        "Time": "00:05:27",
        "AVLS": "00:06:07",
        "Tram": "5007",
        "Action": "a",
        "Msg Sent": "10/11/2019 13:50:58",
        "Msg Received": "10/11/2019 13:50:59",
        "Msg Processed": "10/11/2019 13:50:59",
        "XML ID": "9662",
        "Total Lag": "1.3387994",
        "Create Lag": "1.1981717",
        "Process Lag": "0.1406277"
      },
      {
        "Direction": "Outbound",
        "Destination": "Bride's Glen",
        "Time": "00:16:18",
        "AVLS": "00:16:58",
        "Tram": "5008",
        "Action": "a",
        "Msg Sent": "10/11/2019 13:50:58",
        "Msg Received": "10/11/2019 13:50:59",
        "Msg Processed": "10/11/2019 13:50:59",
        "XML ID": "9662",
        "Total Lag": "1.3856764",
        "Create Lag": "1.1981717",
        "Process Lag": "0.1875047"
      }
    ]
  },
  {
    "stopID": "53",
    "stopQueryDate": "2019-11-10T13:51:01.575Z",
    "count": 4,
    "results": [
      {
        "Direction": "Inbound",
        "Destination": "Belgard",
        "Time": "00:04:22",
        "AVLS": "00:05:02",
        "Tram": "4013",
        "Action": "d",
        "Msg Sent": "10/11/2019 13:50:58",
        "Msg Received": "10/11/2019 13:50:59",
        "Msg Processed": "10/11/2019 13:50:59",
        "XML ID": "9662",
        "Total Lag": "1.2294302",
        "Create Lag": "1.1981717",
        "Process Lag": "0.0312585"
      },
      {
        "Direction": "Inbound",
        "Destination": "Belgard",
        "Time": "00:15:22",
        "AVLS": "00:16:02",
        "Tram": "3019",
        "Action": "d",
        "Msg Sent": "10/11/2019 13:50:58",
        "Msg Received": "10/11/2019 13:50:58",
        "Msg Processed": "10/11/2019 13:50:58",
        "XML ID": "9661",
        "Total Lag": "0.931201",
        "Create Lag": "0.7280626",
        "Process Lag": "0.2031384"
      },
      {
        "Direction": "Terminating",
        "Destination": "Saggart",
        "Time": "00:02:01",
        "AVLS": "00:02:41",
        "Tram": "3019",
        "Action": "a",
        "Msg Sent": "10/11/2019 13:50:58",
        "Msg Received": "10/11/2019 13:50:58",
        "Msg Processed": "10/11/2019 13:50:58",
        "XML ID": "9661",
        "Total Lag": "0.931201",
        "Create Lag": "0.7280626",
        "Process Lag": "0.2031384"
      },
      {
        "Direction": "Terminating",
        "Destination": "Saggart",
        "Time": "00:13:22",
        "AVLS": "00:14:02",
        "Tram": "3026",
        "Action": "a",
        "Msg Sent": "10/11/2019 13:50:58",
        "Msg Received": "10/11/2019 13:50:58",
        "Msg Processed": "10/11/2019 13:50:59",
        "XML ID": "9661",
        "Total Lag": "1.0575471",
        "Create Lag": "0.7280626",
        "Process Lag": "0.3294845"
      }
    ]
  },
  {
    "stopID": "54",
    "stopQueryDate": "2019-11-10T13:51:01.585Z",
    "count": 4,
    "results": [
      {
        "Direction": "Inbound",
        "Destination": "The Point",
        "Time": "00:06:38",
        "AVLS": "00:07:18",
        "Tram": "3006",
        "Action": "a",
        "Msg Sent": "10/11/2019 13:50:58",
        "Msg Received": "10/11/2019 13:50:58",
        "Msg Processed": "10/11/2019 13:50:58",
        "XML ID": "9661",
        "Total Lag": "0.774944",
        "Create Lag": "0.7280626",
        "Process Lag": "0.0468814"
      },
      {
        "Direction": "Inbound",
        "Destination": "The Point",
        "Time": "00:18:31",
        "AVLS": "00:19:11",
        "Tram": "4005",
        "Action": "a",
        "Msg Sent": "10/11/2019 13:50:58",
        "Msg Received": "10/11/2019 13:50:59",
        "Msg Processed": "10/11/2019 13:50:59",
        "XML ID": "9662",
        "Total Lag": "1.2294302",
        "Create Lag": "1.1981717",
        "Process Lag": "0.0312585"
      },
      {
        "Direction": "Outbound",
        "Destination": "Tallaght",
        "Time": "00:00:15",
        "AVLS": "00:00:55",
        "Tram": "4002",
        "Action": "a",
        "Msg Sent": "10/11/2019 13:50:58",
        "Msg Received": "10/11/2019 13:50:58",
        "Msg Processed": "10/11/2019 13:50:59",
        "XML ID": "9661",
        "Total Lag": "1.0575471",
        "Create Lag": "0.7280626",
        "Process Lag": "0.3294845"
      },
      {
        "Direction": "Outbound",
        "Destination": "Tallaght",
        "Time": "00:10:58",
        "AVLS": "00:11:38",
        "Tram": "3011",
        "Action": "a",
        "Msg Sent": "10/11/2019 13:50:58",
        "Msg Received": "10/11/2019 13:50:58",
        "Msg Processed": "10/11/2019 13:50:58",
        "XML ID": "9661",
        "Total Lag": "0.8061905",
        "Create Lag": "0.7280626",
        "Process Lag": "0.0781279"
      }
    ]
  },
  {
    "stopID": "52",
    "stopQueryDate": "2019-11-10T13:51:01.594Z",
    "count": 4,
    "results": [
      {
        "Direction": "Inbound",
        "Destination": "Belgard",
        "Time": "00:06:37",
        "AVLS": "00:07:17",
        "Tram": "4013",
        "Action": "a",
        "Msg Sent": "10/11/2019 13:50:58",
        "Msg Received": "10/11/2019 13:50:59",
        "Msg Processed": "10/11/2019 13:50:59",
        "XML ID": "9662",
        "Total Lag": "1.2294302",
        "Create Lag": "1.1981717",
        "Process Lag": "0.0312585"
      },
      {
        "Direction": "Inbound",
        "Destination": "Belgard",
        "Time": "00:17:37",
        "AVLS": "00:18:17",
        "Tram": "3019",
        "Action": "a",
        "Msg Sent": "10/11/2019 13:50:58",
        "Msg Received": "10/11/2019 13:50:58",
        "Msg Processed": "10/11/2019 13:50:58",
        "XML ID": "9661",
        "Total Lag": "0.931201",
        "Create Lag": "0.7280626",
        "Process Lag": "0.2031384"
      },
      {
        "Direction": "Outbound",
        "Destination": "Saggart",
        "Time": "00:00:00",
        "AVLS": "00:00:28",
        "Tram": "3019",
        "Action": "a",
        "Msg Sent": "10/11/2019 13:50:58",
        "Msg Received": "10/11/2019 13:50:58",
        "Msg Processed": "10/11/2019 13:50:58",
        "XML ID": "9661",
        "Total Lag": "0.931201",
        "Create Lag": "0.7280626",
        "Process Lag": "0.2031384"
      },
      {
        "Direction": "Outbound",
        "Destination": "Saggart",
        "Time": "00:11:09",
        "AVLS": "00:11:49",
        "Tram": "3026",
        "Action": "a",
        "Msg Sent": "10/11/2019 13:50:58",
        "Msg Received": "10/11/2019 13:50:58",
        "Msg Processed": "10/11/2019 13:50:59",
        "XML ID": "9661",
        "Total Lag": "1.0575471",
        "Create Lag": "0.7280626",
        "Process Lag": "0.3294845"
      }
    ]
  },
  {
    "stopID": "22",
    "stopQueryDate": "2019-11-10T13:51:01.602Z",
    "count": 4,
    "results": [
      {
        "Direction": "Inbound",
        "Destination": "The Point",
        "Time": "00:04:44",
        "AVLS": "00:05:24",
        "Tram": "3006",
        "Action": "a",
        "Msg Sent": "10/11/2019 13:50:58",
        "Msg Received": "10/11/2019 13:50:58",
        "Msg Processed": "10/11/2019 13:50:58",
        "XML ID": "9661",
        "Total Lag": "0.774944",
        "Create Lag": "0.7280626",
        "Process Lag": "0.0468814"
      },
      {
        "Direction": "Inbound",
        "Destination": "The Point",
        "Time": "00:16:37",
        "AVLS": "00:17:17",
        "Tram": "4005",
        "Action": "a",
        "Msg Sent": "10/11/2019 13:50:58",
        "Msg Received": "10/11/2019 13:50:59",
        "Msg Processed": "10/11/2019 13:50:59",
        "XML ID": "9662",
        "Total Lag": "1.2294302",
        "Create Lag": "1.1981717",
        "Process Lag": "0.0312585"
      },
      {
        "Direction": "Outbound",
        "Destination": "Tallaght",
        "Time": "00:02:11",
        "AVLS": "00:02:51",
        "Tram": "4002",
        "Action": "a",
        "Msg Sent": "10/11/2019 13:50:58",
        "Msg Received": "10/11/2019 13:50:58",
        "Msg Processed": "10/11/2019 13:50:59",
        "XML ID": "9661",
        "Total Lag": "1.0731743",
        "Create Lag": "0.7280626",
        "Process Lag": "0.3451117"
      },
      {
        "Direction": "Outbound",
        "Destination": "Tallaght",
        "Time": "00:12:54",
        "AVLS": "00:13:34",
        "Tram": "3011",
        "Action": "a",
        "Msg Sent": "10/11/2019 13:50:58",
        "Msg Received": "10/11/2019 13:50:58",
        "Msg Processed": "10/11/2019 13:50:58",
        "XML ID": "9661",
        "Total Lag": "0.8061905",
        "Create Lag": "0.7280626",
        "Process Lag": "0.0781279"
      }
    ]
  }
]